Workbook

Sheet Cover & Index
A1: Cover & Index
A3: Cover
A4: B&M / Poundland Acquisition Analysis
A5: Transaction date
A6: Prepared date
A7: Base case
A8: Currency / Units
A9: Confidentiality note if appropriate
A11: Index
A12: Sheet | B12: Purpose
A13: B&M Operating Model | B13: Historical & forecast standalone financials
A14: Poundland Operating Model | B14: Historical & forecast standalone financials
A15: Valuation | B15: DCF & comparable company valuation
A16: M&A Analysis | B16: Transaction structure, purchase price & financing
A17: Synergies & Integration | B17: Synergy build, store rationalisation & integration costs
A18: Accretion & Dilution | B18: Pro forma financials, FCF & EPS impact
A19: Summary & Sensitivities | B19: Key outputs, sensitivities & recommendation

Sheet B&M Operating Model
A1: B&M Historical | J1: B&M Forecast
A3: Financial Year | B3: FY21 | C3: FY22 | D3: FY23 | E3: FY24 | F3: FY25 | J3: Financial Year | K3: FY26E | L3: FY27E | M3: FY28E | N3: FY29E | O3: FY30E
A4: FY End Date | B4: 44282 | C4: 44646 | D4: 45010 | E4: 45381 | F4: 45745 | J4: FY End Date | K4: 46109 | L4: 46473 | M4: 46837 | N4: 47207 | O4: 47571
A6: Income Statement | J6: Operating Assumptions
A7: Revenue (£m) | B7: 4801.425 | C7: 4673 | D7: 4983 | E7: 5484 | F7: 5571 | J7: Revenue Growth | K7: 0.035 | L7: 0.035 | M7: 0.035 | N7: 0.035 | O7: 0.035
A8: Revenue Growth | B8: =(B7/3813.387)-1 -> 0.25909723 | C8: =(C7/B7)-1 -> -0.026747268 | D8: =(D7/C7)-1 -> 0.066338541 | E8: =(E7/D7)-1 -> 0.10054184 | F8: =(F7/E7)-1 -> 0.015864333 | J8: EBITDA Margin | K8: 0.135 | L8: 0.125 | M8: 0.1175 | N8: 0.1075 | O8: 0.0985
A9: EBITDA (£m) | B9: =B11+B24 -> 828.661 | C9: =C11+C24 -> 837 | D9: =D11+D24 -> 778 | E9: =E11+E24 -> 866 | F9: =F11+F24 -> 839 | J9: D&A / Revenue | K9: 0.0485 | L9: 0.048 | M9: 0.0475 | N9: 0.047 | O9: 0.0465
A10: EBITDA Margin | B10: =B9/B7 -> 0.17258647 | C10: =C9/C7 -> 0.17911406 | D10: =D9/D7 -> 0.15613084 | E10: =E9/E7 -> 0.15791393 | F10: =F9/F7 -> 0.15060133 | J10: Capex / Revenue | K10: 0.0239 | L10: 0.0246 | M10: 0.0254 | N10: 0.0262 | O10: 0.027
A11: EBIT (Operating Profit) (£m) | B11: 613.414 | C11: 610 | D11: 536 | E11: 608 | F11: 566 | J11: Tax Rate | K11: 0.25 | L11: 0.25 | M11: 0.25 | N11: 0.25 | O11: 0.25
A12: EBIT Margin | B12: =B11/B7 -> 0.12775666 | C12: =C11/C7 -> 0.13053713 | D12: =D11/D7 -> 0.10756572 | E12: =E11/E7 -> 0.11086798 | F12: =F11/F7 -> 0.10159756 | J12: NWC / Revenue | K12: 0.06 | L12: 0.06 | M12: 0.06 | N12: 0.06 | O12: 0.06
A13: Net Income / Profit After Tax (£m) | B13: 428.104 | C13: 422 | D13: 348 | E13: 367 | F13: 319
A14: Net Income Margin | B14: =B13/B7 -> 0.089161863 | C14: =C13/C7 -> 0.090306013 | D14: =D13/D7 -> 0.069837447 | E14: =E13/E7 -> 0.066921955 | F14: =F13/F7 -> 0.057260815 | J14: Income Statement
J15: Revenue (£m) | K15: =F7*(1+K16) -> 5765.985 | L15: =K15*(1+L16) -> 5967.7945 | M15: =L15*(1+M16) -> 6176.6673 | N15: =M15*(1+N16) -> 6392.8506 | O15: =N15*(1+O16) -> 6616.6004
A16: Balance Sheet | J16: Revenue Growth | K16: =K7 -> 0.035 | L16: =L7 -> 0.035 | M16: =M7 -> 0.035 | N16: =N7 -> 0.035 | O16: =O7 -> 0.035
A17: Cash and Cash Eq. (£m) | B17: 217.682 | C17: 173 | D17: 237 | E17: 182 | F17: 217 | J17: EBITDA (£m) | K17: =K15*K18 -> 778.40797 | L17: =L15*L18 -> 745.97431 | M17: =M15*M18 -> 725.75841 | N17: =N15*N18 -> 687.23144 | O17: =O15*O18 -> 651.73514
A18: Total Debt / Borrowings (£m) | B18: 737 | C18: 963 | D18: 961 | E18: 919 | F18: 1148 | J18: EBITDA Margin | K18: =K8 -> 0.135 | L18: =L8 -> 0.125 | M18: =M8 -> 0.1175 | N18: =N8 -> 0.1075 | O18: =O8 -> 0.0985
A19: Lease Liabilities (£m) | B19: 1301.369 | C19: 1310 | D19: 1301 | E19: 1357 | F19: 1430 | J19: Depreciation & Amortisation (£m) | K19: =K15*K9 -> 279.65027 | L19: =L15*L9 -> 286.45413 | M19: =M15*M9 -> 293.3917 | N19: =N15*N9 -> 300.46398 | O19: =O15*O9 -> 307.67192
A20: Net Debt (excl. leases) (£m) | B20: =B18-B17 -> 519.318 | C20: =C18-C17 -> 790 | D20: =D18-D17 -> 724 | E20: =E18-E17 -> 737 | F20: =F18-F17 -> 931 | J20: EBIT (Operating Profit) (£m) | K20: =K17-K19 -> 498.7577 | L20: =L17-L19 -> 459.52017 | M20: =M17-M19 -> 432.36671 | N20: =N17-N19 -> 386.76746 | O20: =O17-O19 -> 344.06322
A21: Net Debt / EBITDA | B21: =B20/B9 -> 0.62669536 | C21: =C20/C9 -> 0.94384707 | D21: =D20/D9 -> 0.93059126 | E21: =E20/E9 -> 0.85103926 | F21: =F20/F9 -> 1.1096544 | J21: EBIT Margin | K21: =K20/K15 -> 0.0865 | L21: =L20/L15 -> 0.077 | M21: =M20/M15 -> 0.07 | N21: =N20/N15 -> 0.0605 | O21: =O20/O15 -> 0.052
J22: Interest | K22: =Valuation!B14*'B&M Operating Model'!F18 -> 76.5716 | L22: =Valuation!B14*'B&M Operating Model'!F18 -> 76.5716 | M22: =Valuation!B14*'B&M Operating Model'!F18 -> 76.5716 | N22: =Valuation!B14*'B&M Operating Model'!F18 -> 76.5716 | O22: =Valuation!B14*'B&M Operating Model'!F18 -> 76.5716
A23: Cash Flow | J23: PBT | K23: =K20-K22 -> 422.1861 | L23: =L20-L22 -> 382.94857 | M23: =M20-M22 -> 355.79511 | N23: =N20-N22 -> 310.19586 | O23: =O20-O22 -> 267.49162
A24: Depreciation & Amortisation (£m) | B24: 215.247 | C24: 227 | D24: 242 | E24: 258 | F24: 273 | J24: Tax | K24: =K23*Valuation!B10 -> 105.54653 | L24: =L23*Valuation!B10 -> 95.737144 | M24: =M23*Valuation!B10 -> 88.948777 | N24: =N23*Valuation!B10 -> 77.548966 | O24: =O23*Valuation!B10 -> 66.872905
A25: Capital Expenditure (£m) | B25: 87.918 | C25: 100 | D25: 98 | E25: 126 | F25: 133 | J25: Net Income / Profit After Tax (£m) | K25: =K23-K24 -> 316.63958 | L25: =L23-L24 -> 287.21143 | M25: =M23-M24 -> 266.84633 | N25: =N23-N24 -> 232.6469 | O25: =O23-O24 -> 200.61872
A26: Net Working Capital | B26: =605.126+42.16-524.26 -> 123.026 | C26: =863+53-564 -> 352 | D26: =764+52-541 -> 275 | E26: =776+76-572 -> 280 | F26: =883+79-618 -> 344
A27: Change in Net Working Capital (£m) | B27: =B26-(588+60.588-419.999) -> -105.563 | C27: =C26-B26 -> 228.974 | D27: =D26-C26 -> -77 | E27: =E26-D26 -> 5 | F27: =F26-E26 -> 64 | J27: Cash Flow
A28: Cash Flow from Operations (£m) | B28: 944.048 | C28: 598 | D28: 866 | E28: 862 | F28: 784 | J28: Capital Expenditure (£m) | K28: =K15*K29 -> 137.80704 | L28: =L15*L29 -> 146.80774 | M28: =M15*M29 -> 156.88735 | N28: =N15*N29 -> 167.49269 | O28: =O15*O29 -> 178.64821
A29: Cash Tax Paid (£m) | B29: 117.422 | C29: 107 | D29: 84 | E29: 116 | F29: 109 | J29: Capex / Revenue | K29: =K10 -> 0.0239 | L29: =L10 -> 0.0246 | M29: =M10 -> 0.0254 | N29: =N10 -> 0.0262 | O29: =O10 -> 0.027
A30: Interest Paid (£m) | B30: 61.411 | C30: 59 | D30: 61 | E30: 69 | F30: 77 | J30: Net Working Capital | K30: =K15*K12 -> 345.9591 | L30: =L15*L12 -> 358.06767 | M30: =M15*M12 -> 370.60004 | N30: =N15*N12 -> 383.57104 | O30: =O15*O12 -> 396.99602
A31: Free Cash Flow (£m) | B31: =B28-B25-B29 -> 738.708 | C31: =C28-C25-C29 -> 391 | D31: =D28-D25-D29 -> 684 | E31: =E28-E25-E29 -> 620 | F31: =F28-F25-F29 -> 542 | J31: Change in Net Working Capital (£m) | K31: =K30-F26 -> 1.9591 | L31: =L30-K30 -> 12.108568 | M31: =M30-L30 -> 12.532368 | N31: =N30-M30 -> 12.971001 | O31: =O30-N30 -> 13.424986
A32: FCF Margin | B32: =B31/B7 -> 0.15385183 | C32: =C31/C7 -> 0.083672159 | D32: =D31/D7 -> 0.13726671 | E32: =E31/E7 -> 0.11305616 | F32: =F31/F7 -> 0.097289535 | J32: Cash Tax Paid (£m) | K32: =K20*K11 -> 124.68943 | L32: =L20*L11 -> 114.88004 | M32: =M20*M11 -> 108.09168 | N32: =N20*N11 -> 96.691866 | O32: =O20*O11 -> 86.015805
A33: Capex / Revenue | B33: =B25/B7 -> 0.018310814 | C33: =C25/C7 -> 0.021399529 | D33: =D25/D7 -> 0.019666867 | E33: =E25/E7 -> 0.02297593 | F33: =F25/F7 -> 0.023873631 | J33: Free Cash Flow (£m) | K33: =K20-K32+K19-K28-K31 -> 513.95241 | L33: =L20-L32+L19-L28-L31 -> 472.17795 | M33: =M20-M32+M19-M28-M31 -> 448.24701 | N33: =N20-N32+N19-N28-N31 -> 410.07589 | O33: =O20-O32+O19-O28-O31 -> 373.64614
A34: D&A / Revenue | B34: =B24/B7 -> 0.044829816 | C34: =C24/C7 -> 0.048576931 | D34: =D24/D7 -> 0.048565121 | E34: =E24/E7 -> 0.047045952 | F34: =F24/F7 -> 0.04900377 | J34: FCF Margin | K34: =K33/K15 -> 0.089135232 | L34: =L33/L15 -> 0.079121014 | M34: =M33/M15 -> 0.072571014 | N34: =N33/N15 -> 0.064146014 | O34: =O33/O15 -> 0.056471014
A35: NWC / Revenue | B35: =B26/B7 -> 0.02562281 | C35: =C26/C7 -> 0.075326343 | D35: =D26/D7 -> 0.055187638 | E35: =E26/E7 -> 0.051057622 | F35: =F26/F7 -> 0.06174834
J36: Assumption Notes
J37: Revenue growth | K37: FY22-25 simple average 3.9%, Indistry forecast 3.5%
J38: EBITDA Margin | K38: FY23-25 average of 15.5%, hard to maintains so gradual to industry at 9.85%
J39: D&A / Revenue | K39: Very stable with average of 4.8% between FY22-25 but gradual decline
J40: Capex / Revenue | K40: Slow gradual increase due to expansion to new stores
J41: Tax Rate | K41: Use UK corporation tax rate of 25%
J42: NWC / Revenue | K42: Simple avg FY22-25 is 6.1%, FY23-25 5.6% so use stable 6%

Sheet Poundland Operating Model
A1: Poundland Historical | J1: Poundland Forecast
A3: Financial Year | B3: FY21 | C3: FY22 | D3: FY23 | E3: FY24 | F3: FY25 | J3: Financial Year | K3: FY26E | L3: FY27E | M3: FY28E | N3: FY29E | O3: FY30E
A4: FY End Date | B4: 44465 | C4: 44829 | D4: 45200 | E4: 45564 | F4: 45928 | J4: FY End Date | K4: 46292 | L4: 46656 | M4: 47027 | N4: 47391 | O4: 47755
A6: Income Statement | J6: Operating Assumptions
A7: Revenue (£m) | B7: 1544.694 | C7: 1586.1 | D7: 1771.723 | E7: 1757.021 | F7: 1549.073 | J7: Revenue Growth | K7: -0.05 | L7: 0.015 | M7: 0.025 | N7: 0.035 | O7: 0.035
A8: Revenue Growth | B8: =(B7/1476.64)-1 -> 0.046087063 | C8: =(C7/B7)-1 -> 0.026805309 | D8: =(D7/C7)-1 -> 0.11703108 | E8: =(E7/D7)-1 -> -0.0082981369 | F8: =(F7/E7)-1 -> -0.1183526 | J8: EBITDA Margin | K8: 0.035 | L8: 0.04 | M8: 0.05 | N8: 0.065 | O8: 0.065
A9: EBITDA (£m) | B9: =B11+B24 -> 179.206 | C9: =C11+C24 -> 173.877 | D9: =D11+D24 -> 171.698 | E9: =E11+E24 -> 115.506 | F9: =F11+F24 -> 22.93 | J9: D&A / Revenue | K9: 0.045 | L9: 0.043 | M9: 0.041 | N9: 0.04 | O9: 0.04
A10: EBITDA Margin | B10: =B9/B7 -> 0.11601392 | C10: =C9/C7 -> 0.1096255 | D10: =D9/D7 -> 0.096910183 | E10: =E9/E7 -> 0.065739681 | F10: =F9/F7 -> 0.014802401 | J10: Capex / Revenue | K10: 0.03 | L10: 0.034 | M10: 0.036 | N10: 0.038 | O10: 0.04
A11: EBIT (Operating Profit) (£m) | B11: 54.095 | C11: 55.645 | D11: 25.173 | E11: -17.726 | F11: -49.986 | J11: Tax Rate | K11: 0.25 | L11: 0.25 | M11: 0.25 | N11: 0.25 | O11: 0.25
A12: EBIT Margin | B12: =B11/B7 -> 0.035019881 | C12: =C11/C7 -> 0.035082908 | D12: =D11/D7 -> 0.014208203 | E12: =E11/E7 -> -0.010088667 | F12: =F11/F7 -> -0.032268331 | J12: NWC / Revenue | K12: -0.02 | L12: -0.02 | M12: -0.02 | N12: -0.02 | O12: -0.02
A13: Net Income / Profit After Tax (£m) | B13: 37.084 | C13: 25.129 | D13: 2.092 | E13: -57.034 | F13: -120.49
A14: Net Income Margin | B14: =B13/B7 -> 0.024007344 | C14: =C13/C7 -> 0.015843263 | D14: =D13/D7 -> 0.0011807715 | E14: =E13/E7 -> -0.032460625 | F14: =F13/F7 -> -0.077782003 | J14: Income Statement
J15: Revenue (£m) | K15: =F7*(1+K16) -> 1471.6193 | L15: =K15*(1+L16) -> 1493.6936 | M15: =L15*(1+M16) -> 1531.036 | N15: =M15*(1+N16) -> 1584.6222 | O15: =N15*(1+O16) -> 1640.084
A16: Balance Sheet | J16: Revenue Growth | K16: =K7 -> -0.05 | L16: =L7 -> 0.015 | M16: =M7 -> 0.025 | N16: =N7 -> 0.035 | O16: =O7 -> 0.035
A17: Cash and Cash Eq. (£m) | B17: 71.611 | C17: 42.771 | D17: 41.864 | E17: 46.72 | F17: 30.636 | J17: EBITDA (£m) | K17: =K15*K18 -> 51.506677 | L17: =L15*L18 -> 59.747746 | M17: =M15*M18 -> 76.551799 | N17: =N15*N18 -> 103.00045 | O17: =O15*O18 -> 106.60546
A18: Total Debt / Borrowings (£m) | B18: 89.609 | C18: 99.126 | D18: 108.376 | E18: 228.573 | F18: 78.095 | J18: EBITDA Margin | K18: =K8 -> 0.035 | L18: =L8 -> 0.04 | M18: =M8 -> 0.05 | N18: =N8 -> 0.065 | O18: =O8 -> 0.065
A19: Lease Liabilities (£m) | B19: 350.932 | C19: 394.475 | D19: 411.113 | E19: 502.396 | F19: 277.495 | J19: Depreciation & Amortisation (£m) | K19: =K15*K9 -> 66.222871 | L19: =L15*L9 -> 64.228827 | M19: =M15*M9 -> 62.772475 | N19: =N15*N9 -> 63.38489 | O19: =O15*O9 -> 65.603361
A20: Net Debt (excl. leases) (£m) | B20: =B18-B17 -> 17.998 | C20: =C18-C17 -> 56.355 | D20: =D18-D17 -> 66.512 | E20: =E18-E17 -> 181.853 | F20: =F18-F17 -> 47.459 | J20: EBIT (Operating Profit) (£m) | K20: =K17-K19 -> -14.716193 | L20: =L17-L19 -> -4.4810809 | M20: =M17-M19 -> 13.779324 | N20: =N17-N19 -> 39.615556 | O20: =O17-O19 -> 41.0021
A21: Net Debt / EBITDA | B21: =B20/B9 -> 0.10043191 | C21: =C20/C9 -> 0.32410842 | D21: =D20/D9 -> 0.38737784 | E21: =E20/E9 -> 1.5744031 | F21: =F20/F9 -> 2.069734 | J21: EBIT Margin | K21: =K20/K15 -> -0.01 | L21: =L20/L15 -> -0.003 | M21: =M20/M15 -> 0.009 | N21: =N20/N15 -> 0.025 | O21: =O20/O15 -> 0.025
J22: Interest | K22: =Valuation!K15*'Poundland Operating Model'!F18 -> 5.076175 | L22: =Valuation!K15*'Poundland Operating Model'!F18 -> 5.076175 | M22: =Valuation!K15*'Poundland Operating Model'!F18 -> 5.076175 | N22: =Valuation!K15*'Poundland Operating Model'!F18 -> 5.076175 | O22: =Valuation!K15*'Poundland Operating Model'!F18 -> 5.076175
A23: Cash Flow | J23: PBT | K23: =K20-K22 -> -19.792368 | L23: =L20-L22 -> -9.5572559 | M23: =M20-M22 -> 8.7031488 | N23: =N20-N22 -> 34.539381 | O23: =O20-O22 -> 35.925925
A24: Depreciation & Amortisation (£m) | B24: 125.111 | C24: 118.232 | D24: 146.525 | E24: 133.232 | F24: 72.916 | J24: Tax | K24: =K23*Valuation!B10 -> -4.9480921 | L24: =L23*Valuation!B10 -> -2.389314 | M24: =M23*Valuation!B10 -> 2.1757872 | N24: =N23*Valuation!B10 -> 8.6348453 | O24: =O23*Valuation!B10 -> 8.9814814
A25: Capital Expenditure (£m) | B25: =63.469+7.536 -> 71.005 | C25: =125.075+1.601 -> 126.676 | D25: =137.545+1.423 -> 138.968 | E25: =120.756+1.813 -> 122.569 | F25: =38.027+0.237 -> 38.264 | J25: Net Income / Profit After Tax (£m) | K25: =K23-K24 -> -14.844276 | L25: =L23-L24 -> -7.1679419 | M25: =M23-M24 -> 6.5273616 | N25: =N23-N24 -> 25.904536 | O25: =O23-O24 -> 26.944444
A26: Net Working Capital | B26: =191.541+86.944-275.38 -> 3.105 | C26: =215.088+131.578-325.855 -> 20.811 | D26: =217.333+136.004-416.915 -> -63.578 | E26: =230.375+131.968-385.499 -> -23.156 | F26: =164.922+58.085-255.27 -> -32.263
A27: Change in Net Working Capital (£m) | B27: =B26-(-21.29) -> 24.395 | C27: =C26-B26 -> 17.706 | D27: =D26-C26 -> -84.389 | E27: =E26-D26 -> 40.422 | F27: =F26-E26 -> -9.107 | J27: Cash Flow
A28: Cash Flow from Operations (£m) | B28: =B13+B24-B27 -> 137.8 | C28: =C13+C24-C27 -> 125.655 | D28: =D13+D24-D27 -> 233.006 | E28: =E13+E24-E27 -> 35.776 | F28: =F13+F24-F27 -> -38.467 | J28: Capital Expenditure (£m) | K28: =K15*K29 -> 44.14858 | L28: =L15*L29 -> 50.785584 | M28: =M15*M29 -> 55.117295 | N28: =N15*N29 -> 60.215645 | O28: =O15*O29 -> 65.603361
A29: Cash Tax Paid (£m) | B29: =5.634-(0-0.013) -> 5.647 | C29: =4.556 -> 4.556 | D29: 5.93 | E29: -3.124 | F29: -0.777 | J29: Capex / Revenue | K29: =K10 -> 0.03 | L29: =L10 -> 0.034 | M29: =M10 -> 0.036 | N29: =N10 -> 0.038 | O29: =O10 -> 0.04
A30: Interest Paid (£m) | B30: =21.112-0.495 -> 20.617 | C30: =23.097-1.372 -> 21.725 | D30: =25.829-1.336 -> 24.493 | E30: =29.184-1.527 -> 27.657 | F30: =34.722-1.646 -> 33.076 | J30: Net Working Capital | K30: =K15*K12 -> -29.432387 | L30: =L15*L12 -> -29.873873 | M30: =M15*M12 -> -30.62072 | N30: =N15*N12 -> -31.692445 | O30: =O15*O12 -> -32.80168
A31: Free Cash Flow (£m) | B31: =B28-B25-B29 -> 61.148 | C31: =C28-C25-C29 -> -5.577 | D31: =D28-D25-D29 -> 88.108 | E31: =E28-E25-E29 -> -83.669 | F31: =F28-F25-F29 -> -75.954 | J31: Change in Net Working Capital (£m) | K31: =K30-F26 -> 2.830613 | L31: =L30-K30 -> -0.4414858 | M31: =M30-L30 -> -0.74684682 | N31: =N30-M30 -> -1.0717252 | O31: =O30-N30 -> -1.1092356
A32: FCF Margin | B32: =B31/B7 -> 0.039585834 | C32: =C31/C7 -> -0.0035161717 | D32: =D31/D7 -> 0.049730121 | E32: =E31/E7 -> -0.047619806 | F32: =F31/F7 -> -0.049031905 | J32: Cash Tax Paid (£m) | K32: =K20*K11 -> -3.6790484 | L32: =L20*L11 -> -1.1202702 | M32: =M20*M11 -> 3.444831 | N32: =N20*N11 -> 9.903889 | O32: =O20*O11 -> 10.250525
A33: Capex / Revenue | B33: =B25/B7 -> 0.045967033 | C33: =C25/C7 -> 0.079866339 | D33: =D25/D7 -> 0.07843664 | E33: =E25/E7 -> 0.069759553 | F33: =F25/F7 -> 0.024701225 | J33: Free Cash Flow (£m) | K33: =K20-K32+K19-K28-K31 -> 8.2065321 | L33: =L20-L32+L19-L28-L31 -> 10.523918 | M33: =M20-M32+M19-M28-M31 -> 18.73652 | N33: =N20-N32+N19-N28-N31 -> 33.952637 | O33: =O20-O32+O19-O28-O31 -> 31.860811
A34: D&A / Revenue | B34: =B24/B7 -> 0.080994035 | C34: =C24/C7 -> 0.074542589 | D34: =D24/D7 -> 0.08270198 | E34: =E24/E7 -> 0.075828348 | F34: =F24/F7 -> 0.047070732 | J34: FCF Margin | K34: =K33/K15 -> 0.0055765318 | L34: =L33/L15 -> 0.0070455665 | M34: =M33/M15 -> 0.012237805 | N34: =N33/N15 -> 0.021426329 | O34: =O33/O15 -> 0.019426329
A35: NWC / Revenue | B35: =B26/B7 -> 0.0020101069 | C35: =C26/C7 -> 0.013120862 | D35: =D26/D7 -> -0.035884842 | E35: =E26/E7 -> -0.013179125 | F35: =F26/F7 -> -0.020827295
J36: Forecast Notes
J37: Revenue Growth | K37: Currently restructuring, then begin recovery until industies expected
J38: EBITDA Margin | K38: Slow recovery after restructuring but firm operates differently so 10-12% may no longer be possible
J39: D&A / Revenue | K39: Stable FY21-24 at 7.9%, close stores that had higher D&A and make improvements so steady decline
J40: Capex / Revenue | K40: Less at first then FY21-24 average of 6.85%, similar to D&A so 6.85*(650/800)*0.7=3.89 so use 4% terminal
J41: Tax Rate | K41: Use UK corporation tax rate of 25%
J42: NWC / Revenue | K42: FY23-25 average of -2.3%, assume stays fairly similar to average and to FY25 of -2%

Sheet Valuation
A1: DCF Valuation
A5: DCF Assumptions | B5: Value | C5: Source / Assumption
A6: Valuation Date | B6: 46255 | C6: Transaction Analysis Date
A7: Risk-Free Rate | B7: 0.050639 | C7: UK 10-year gilt yield at close
A8: Equity Risk Premium | B8: 0.0498 | C8: Damodaran UK Equity Risk Premium, July 2026
A9: Terminal Growth Rate | B9: 0.02 | C9: Long-term conservative nominal growth assumption
A10: Tax Rate | B10: 0.25 | C10: Forecast assumption
A12: B&M WACC | J12: Poundland WACC
A13: Beta | B13: 1.09 | C13: B&M European Value Retail beta | J13: Unlevered Beta | K13: 0.84 | L13: Damodaran's Jan 2026 global data for retail (special lines)
A14: Pre-Tax Cost of Debt | B14: 0.0667 | C14: Average FY22-25 implied pre-tax cost of debt calculated as interst paid / total debt/borrowings | J14: Re-Levered Beta | K14: =K13*(1+(1-B10)*(K16/K17)) -> 0.9975 | L14: Calculation
A15: Debt / Total Capital | B15: ='B&M Operating Model'!F18/('B&M Operating Model'!F18+(1005.038256*2.364)) -> 0.32577445 | C15: Calculation using market equity value on 21/08/2026 and FY25 total debt/borrowings | J15: Pre-Tax Cost of Debt | K15: 0.065 | L15: The stated interest rate on Poundland's secured loan following the 2025 restructuring
A16: Equity / Total Capital | B16: =1-B15 -> 0.67422555 | C16: Calculation | J16: Debt / Total Capital | K16: 0.2 | L16: Assume conservative 20% benchmarked against calculations with Damdaran's D/E to get 15.5% D/C
A17: Cost of Equity | B17: =B7+(B13*B8) -> 0.104921 | C17: Formula | J17: Equity / Total Capital | K17: =1-K16 -> 0.8 | L17: Calculation
A18: After-Tax Cost of Debt | B18: =B14*(1-B10) -> 0.050025 | C18: Formula | J18: Cost of Equity | K18: =B7+(K14*B8) -> 0.1003145 | L18: Formula
A19: WACC | B19: =(B16*B17)+(B15*B18) -> 0.087037286 | C19: Formula | J19: After-Tax Cost of Debt | K19: =K15*(1-B10) -> 0.04875 | L19: Formula
J20: WACC | K20: =(K17*K18)+(K16*K19) -> 0.0900016 | L20: Formula
A24: B&M DCF | J24: Poundland DCF
A25: Financial Year | B25: FY26E | C25: FY27E | D25: FY28E | E25: FY29E | F25: FY30E | J25: Financial Year | K25: FY26E | L25: FY27E | M25: FY28E | N25: FY29E | O25: FY30E
A26: EBIT (Operating Profit) (£m) | B26: ='B&M Operating Model'!K20 -> 498.7577 | C26: ='B&M Operating Model'!L20 -> 459.52017 | D26: ='B&M Operating Model'!M20 -> 432.36671 | E26: ='B&M Operating Model'!N20 -> 386.76746 | F26: ='B&M Operating Model'!O20 -> 344.06322 | J26: EBIT (Operating Profit) (£m) | K26: ='Poundland Operating Model'!K20 -> -14.716193 | L26: ='Poundland Operating Model'!L20 -> -4.4810809 | M26: ='Poundland Operating Model'!M20 -> 13.779324 | N26: ='Poundland Operating Model'!N20 -> 39.615556 | O26: ='Poundland Operating Model'!O20 -> 41.0021
A27: Tax on EBIT (Less) | B27: =B26*B10 -> 124.68943 | C27: =C26*B10 -> 114.88004 | D27: =D26*B10 -> 108.09168 | E27: =E26*B10 -> 96.691866 | F27: =F26*B10 -> 86.015805 | J27: Tax on EBIT (Less) | K27: =MAX(0,K26*B10) -> 0 | L27: =MAX(0,L26*B10) -> 0 | M27: =MAX(0,M26*B10) -> 3.444831 | N27: =MAX(0,N26*B10) -> 9.903889 | O27: =MAX(0,O26*B10) -> 10.250525
A28: NOPAT | B28: =B26-B27 -> 374.06828 | C28: =C26-C27 -> 344.64013 | D28: =D26-D27 -> 324.27503 | E28: =E26-E27 -> 290.0756 | F28: =F26-F27 -> 258.04742 | J28: NOPAT | K28: =K26-K27 -> -14.716193 | L28: =L26-L27 -> -4.4810809 | M28: =M26-M27 -> 10.334493 | N28: =N26-N27 -> 29.711667 | O28: =O26-O27 -> 30.751575
A29: Depreciation & Amortisation (£m) (Add) | B29: ='B&M Operating Model'!K19 -> 279.65027 | C29: ='B&M Operating Model'!L19 -> 286.45413 | D29: ='B&M Operating Model'!M19 -> 293.3917 | E29: ='B&M Operating Model'!N19 -> 300.46398 | F29: ='B&M Operating Model'!O19 -> 307.67192 | J29: Depreciation & Amortisation (£m) (Add) | K29: ='Poundland Operating Model'!K19 -> 66.222871 | L29: ='Poundland Operating Model'!L19 -> 64.228827 | M29: ='Poundland Operating Model'!M19 -> 62.772475 | N29: ='Poundland Operating Model'!N19 -> 63.38489 | O29: ='Poundland Operating Model'!O19 -> 65.603361
A30: Capital Expenditure (£m) (Less) | B30: ='B&M Operating Model'!K28 -> 137.80704 | C30: ='B&M Operating Model'!L28 -> 146.80774 | D30: ='B&M Operating Model'!M28 -> 156.88735 | E30: ='B&M Operating Model'!N28 -> 167.49269 | F30: ='B&M Operating Model'!O28 -> 178.64821 | J30: Capital Expenditure (£m) (Less) | K30: ='Poundland Operating Model'!K28 -> 44.14858 | L30: ='Poundland Operating Model'!L28 -> 50.785584 | M30: ='Poundland Operating Model'!M28 -> 55.117295 | N30: ='Poundland Operating Model'!N28 -> 60.215645 | O30: ='Poundland Operating Model'!O28 -> 65.603361
A31: Change in Net Working Capital (Less) | B31: ='B&M Operating Model'!K31 -> 1.9591 | C31: ='B&M Operating Model'!L31 -> 12.108568 | D31: ='B&M Operating Model'!M31 -> 12.532368 | E31: ='B&M Operating Model'!N31 -> 12.971001 | F31: ='B&M Operating Model'!O31 -> 13.424986 | J31: Change in Net Working Capital (Less) | K31: ='Poundland Operating Model'!K31 -> 2.830613 | L31: ='Poundland Operating Model'!L31 -> -0.4414858 | M31: ='Poundland Operating Model'!M31 -> -0.74684682 | N31: ='Poundland Operating Model'!N31 -> -1.0717252 | O31: ='Poundland Operating Model'!O31 -> -1.1092356
A32: Unlevered Free Cash Flow | B32: =B28+B29-B30-B31 -> 513.95241 | C32: =C28+C29-C30-C31 -> 472.17795 | D32: =D28+D29-D30-D31 -> 448.24701 | E32: =E28+E29-E30-E31 -> 410.07589 | F32: =F28+F29-F30-F31 -> 373.64614 | J32: Unlevered Free Cash Flow | K32: =K28+K29-K30-K31 -> 4.5274838 | L32: =L28+L29-L30-L31 -> 9.4036476 | M32: =M28+M29-M30-M31 -> 18.73652 | N32: =N28+N29-N30-N31 -> 33.952637 | O32: =O28+O29-O30-O31 -> 31.860811
A33: Discount Factor | B33: =1/(1+B19)^1 -> 0.91993165 | C33: =1/(1+B19)^2 -> 0.84627423 | D33: =1/(1+B19)^3 -> 0.77851445 | E33: =1/(1+B19)^4 -> 0.71618008 | F33: =1/(1+B19)^5 -> 0.65883672 | J33: Discount Factor | K33: =1/(1+K20)^1 -> 0.91742985 | L33: =1/(1+K20)^2 -> 0.84167752 | M33: =1/(1+K20)^3 -> 0.77218008 | N33: =1/(1+K20)^4 -> 0.70842105 | O33: =1/(1+K20)^5 -> 0.64992662
A34: Present Value of Unlevered FCF | B34: =B32*B33 -> 472.80108 | C34: =C32*C33 -> 399.59204 | D34: =D32*D33 -> 348.96678 | E34: =E32*E33 -> 293.68818 | F34: =F32*F33 -> 246.1718 | J34: Present Value of Unlevered FCF | K34: =K32*K33 -> 4.1536487 | L34: =L32*L33 -> 7.9148389 | M34: =M32*M33 -> 14.467967 | N34: =N32*N33 -> 24.052763 | O34: =O32*O33 -> 20.707189
A36: B&M Terminal Value and Valuation | B36: Value | J36: Poundland Terminal Value and Valuation | K36: Value
A37: FY30E Unlevered FCF (£m) | B37: =F32 -> 373.64614 | J37: FY30E Unlevered FCF (£m) | K37: =O32 -> 31.860811
A38: Terminal Growth Rate | B38: =B9 -> 0.02 | J38: Terminal Growth Rate | K38: =B9 -> 0.02
A39: WACC | B39: =B19 -> 0.087037286 | J39: WACC | K39: =K20 -> 0.0900016
A40: Terminal Value (£m) | B40: =B37*(1+B38)/(B39-B38) -> 5685.1804 | J40: Terminal Value (£m) | K40: =K37*(1+K38)/(K39-K38) -> 464.24692
A41: FY30E Discount Factor | B41: =F33 -> 0.65883672 | J41: FY30E Discount Factor | K41: =O33 -> 0.64992662
A42: Present Value of Terminal Value | B42: =B40*B41 -> 3745.6056 | J42: Present Value of Terminal Value | K42: =K40*K41 -> 301.72643
A43: Present Value of Explicit Forecast FCF | B43: =SUM(B34:F34) -> 1761.2199 | J43: Present Value of Explicit Forecast FCF | K43: =SUM(K34:O34) -> 71.296406
A44: Enterprise Value | B44: =B42+B43 -> 5506.8255 | J44: Enterprise Value | K44: =K42+K43 -> 373.02284
A45: Net Debt (Less) | B45: ='B&M Operating Model'!F20 -> 931 | J45: Net Debt (Less) | K45: ='Poundland Operating Model'!F20 -> 47.459
A46: Equity Value | B46: =B44-B45 -> 4575.8255 | J46: Equity Value | K46: =K44-K45 -> 325.56384
A50: B&M Enterprise Value Sensitivity Analysis | J50: Poundland Enterprise Value Sensitivity Analysis
A51: Terminal Growth Rate \ WACC | B51: =C51-0.01 -> 0.067037286 | C51: =D51-0.01 -> 0.077037286 | D51: 0.087037286 | E51: =D51+0.01 -> 0.097037286 | F51: =E51+0.01 -> 0.10703729 | J51: Terminal Growth Rate \ WACC | K51: =L51-0.01 -> 0.0700016 | L51: =M51-0.01 -> 0.0800016 | M51: 0.0900016 | N51: =M51+0.01 -> 0.1000016 | O51: =N51+0.01 -> 0.1100016
A52: =A53-0.01 -> 0 | B52: 5881.245 | C52: 5152.1932 | D52: 4589.5686 | E52: 4141.9652 | F52: 3777.1851 | J52: =J53-0.01 -> 0 | K52: 400.86656 | L52: 344.80934 | M52: 301.37219 | N52: 266.76329 | O52: 238.56987
A53: =A54-0.01 -> 0.01 | B53: 6635.0636 | C53: 5689.8686 | D53: 4988.6637 | E53: 4447.4088 | F53: 4016.7029 | J53: =J54-0.01 -> 0.01 | K53: 458.73588 | L53: 386.62631 | M53: 332.71944 | N53: 290.94162 | O53: 257.64891
A54: 0.02 | B54: 7709.4018 | C54: 6416.0787 | D54: 5506.8255 | E54: 4832.1499 | F54: 4311.2587 | J54: 0.02 | K54: 539.75217 | L54: 442.3819 | M54: 373.02284 | N54: 321.16442 | O54: 280.96765
A55: =A54+0.01 -> 0.03 | B55: 9363.8787 | C55: 7451.0694 | D55: 6206.6795 | E55: 5331.6753 | F55: 4682.2854 | J55: =J54+0.01 -> 0.03 | K55: 661.275 | L55: 520.43902 | M55: 426.76034 | N55: 360.0221 | O55: 310.11597
A56: =A55+0.01 -> 0.04 | B56: 12242.204 | C56: 9044.9513 | D56: 7204.1077 | E56: 6006.3581 | F56: 5164.0048 | J56: =J55+0.01 -> 0.04 | K56: 863.80872 | L56: 637.52313 | M56: 501.99216 | N56: 411.83201 | O56: 347.59219
A60: Standalone Valuation Summary | B60: B&M | C60: Poundland
A61: Enterprise Value | B61: =D54 -> 5506.8255 | C61: =M54 -> 373.02284
A62: Net Debt (Less) | B62: =B45 -> 931 | C62: =K45 -> 47.459
A63: Equity Value | B63: =B61-B62 -> 4575.8255 | C63: =C61-C62 -> 325.56384
B65: 4575.8255
A69: Comparable Companies
A73: Company | B73: B&M | C73: Pepco | D73: Dollar General | E73: Dollar Tree
A74: FX Conversion Rate | B74: 1 | C74: 0.8566 | D74: 0.7329 | E74: 0.7329
A75: Share Price | B75: =B74*2.364 -> 2.364 | C75: =0.1986*42.89 -> 8.517954 | D75: =D74*123.41 -> 90.447189 | E75: =E74*131.48 -> 96.361692
A76: Shares Outstanding (m) | B76: 1005.0383 | C76: 509.57254 | D76: 220.22632 | E76: 187.67294
A77: Equity Value / Market Cap (GBP) (£m) | B77: =B75*B76 -> 2375.9104 | C77: =C75*C76 -> 4340.5154 | D77: =D75*D76 -> 19918.852 | E77: =E75*E76 -> 18084.482
A78: Total Debt / Borrowings (£m) | B78: =B74*998 -> 998 | C78: =C74*627 -> 537.0882 | D78: =D74*4565.881 -> 3346.3342 | E78: =E74*2431.7 -> 1782.1929
A79: Cash & Cash Equivalents (£m) | B79: =B74*342 -> 342 | C79: =C74*464.357 -> 397.76821 | D79: =D74*1138.501 -> 834.40738 | E79: =E74*717.8 -> 526.07562
A80: Net Debt (Less) (£m) | B80: =B78-B79 -> 656 | C80: =C78-C79 -> 139.31999 | D80: =D78-D79 -> 2511.9268 | E80: =E78-E79 -> 1256.1173
A81: Enterprise Value (£m) | B81: =B77+B80 -> 3031.9104 | C81: =C77+C80 -> 4479.8354 | D81: =D77+D80 -> 22430.778 | E81: =E77+E80 -> 19340.599
A82: Revenue (£m) | B82: =B74*5775 -> 5775 | C82: =C74*4523.463 -> 3874.7984 | D82: =D74*42724.369 -> 31312.69 | E82: =E74*19411.8 -> 14226.908
A83: EBITDA (£m) | B83: =B74*(374+297) -> 671 | C83: =C74*(319.874+455.022) -> 663.77591 | D83: =D74*(2203.668+1046.318) -> 2381.9147 | E83: =E74*(1653.1+648.1) -> 1686.5495
A85: Trading Multiples
A86: EV / Revenue | B86: =B81/B82 -> 0.52500614 | C86: =C81/C82 -> 1.1561467 | D86: =D81/D82 -> 0.71634786 | E86: =E81/E82 -> 1.359438
A87: EV / EBITDA | B87: =B81/B83 -> 4.5184954 | C87: =C81/C83 -> 6.7490177 | D87: =D81/D83 -> 9.4171206 | E87: =E81/E83 -> 11.467555
A91: Peer Multiples Summary
A92: Statistic | B92: EV / Revenue | C92: EV / EBITDA
A93: Minimum | B93: =MIN(B86:E86) -> 0.52500614 | C93: =MIN(B87:E87) -> 4.5184954
A94: 25th Percentile | B94: =_xlfn.QUARTILE.INC(B86:E86,1) -> 0.66851243 | C94: =_xlfn.QUARTILE.INC(B87:E87,1) -> 6.1913872
A95: Median | B95: =MEDIAN(B86:E86) -> 0.93624728 | C95: =MEDIAN(B87:E87) -> 8.0830692
A96: Mean | B96: =AVERAGE(B86:E86) -> 0.93923467 | C96: =AVERAGE(B87:E87) -> 8.0380473
A97: 75th Percentile | B97: =_xlfn.QUARTILE.INC(B86:E86,3) -> 1.2069695 | C97: =_xlfn.QUARTILE.INC(B87:E87,3) -> 9.9297293
A98: Maximum | B98: =MAX(B86:E86) -> 1.359438 | C98: =MAX(B87:E87) -> 11.467555
A102: Poundland Implied Valuation | B102: Low | C102: Base | D102: High
A104: EV / Revenue Implied Valuation
A105: FY26E Revenue (£m) | B105: ='Poundland Operating Model'!K15 -> 1471.6193 | C105: ='Poundland Operating Model'!K15 -> 1471.6193 | D105: ='Poundland Operating Model'!K15 -> 1471.6193
A106: Selected EV / Revenue Multiple | B106: =B93-0.5*(B94-B93) -> 0.45325299 | C106: =B93 -> 0.52500614 | D106: =B93+0.5*(B94-B93) -> 0.59675928
A107: Implied Enterprise Value (£m) | B107: =B105*B106 -> 667.01587 | C107: =C105*C106 -> 772.60919 | D107: =D105*D106 -> 878.20251
A108: Net Debt (Less) (£m) | B108: ='Poundland Operating Model'!F20 -> 47.459 | C108: ='Poundland Operating Model'!F20 -> 47.459 | D108: ='Poundland Operating Model'!F20 -> 47.459
A109: Implied Equity Value (£m) | B109: =B107-B108 -> 619.55687 | C109: =C107-C108 -> 725.15019 | D109: =D107-D108 -> 830.74351
A111: Poundland EV / EBITDA Valuation
A112: FY26E EBITDA (£m) | B112: ='Poundland Operating Model'!K17 -> 51.506677 | C112: ='Poundland Operating Model'!K17 -> 51.506677 | D112: ='Poundland Operating Model'!K17 -> 51.506677
A113: Selected EV / EBITDA Multiple | B113: =C93-0.5*(C94-C93) -> 3.6820496 | C113: =C93 -> 4.5184954 | D113: =C93+0.5*(C94-C93) -> 5.3549413
A114: Implied Enterprise Value (£m) | B114: =B112*B113 -> 189.65014 | C114: =C112*C113 -> 232.73269 | D114: =D112*D113 -> 275.81523
A115: Net Debt (Less) (£m) | B115: ='Poundland Operating Model'!F20 -> 47.459 | C115: ='Poundland Operating Model'!F20 -> 47.459 | D115: ='Poundland Operating Model'!F20 -> 47.459
A116: Implied Equity Value (£m) | B116: =B114-B115 -> 142.19114 | C116: =C114-C115 -> 185.27369 | D116: =D114-D115 -> 228.35623
A120: Poundland Final Standalone Valuation | B120: Low | C120: Base | D120: High
A121: DCF Enterprise Value | B121: =N53 -> 290.94162 | C121: =M54 -> 373.02284 | D121: =L55 -> 520.43902
A122: DCF Equity Value | B122: =B121-K45 -> 243.48262 | C122: =C121-K45 -> 325.56384 | D122: =D121-K45 -> 472.98002
A123: Comparable Enterprise Value | B123: =0.3*B107+0.7*B114 -> 332.85986 | C123: =0.3*C107+0.7*C114 -> 394.69564 | D123: =0.3*D107+0.7*D114 -> 456.53141
A124: Comparable Equity Value | B124: =0.3*B109+0.7*B116 -> 285.40086 | C124: =0.3*C109+0.7*C116 -> 347.23664 | D124: =0.3*D109+0.7*D116 -> 409.07241
A125: Blended Equity Value | B125: =(B122+B124)/2 -> 264.44174 | C125: =(C122+C124)/2 -> 336.40024 | D125: =(D122+D124)/2 -> 441.02622
A129: Notes
A130: EV / Revenue Multiple selection | B130: Used minimum of comps (B&M) because weak after restructuring, half of distance between min and 25th either side
A131: EV / EBITDA Multiple selection | B131: Used minimum of comps (B&M) because weak after restructuring, half of distance between min and 25th either side
A132: Selected Comparable Weightings | B132: 70/30 weighting towards EV / EBITDA to put emphasis on profitability after restructuring
A133: Blended Equity Weightings | B133: 50/50

Sheet M&A Analysis
A1: M&A Analysis
A5: Transaction Overview | B5: Value | C5: Assumption
A6: Transaction Date | B6: 46255
A7: Acquirer | B7: B&M
A8: Target | B8: Poundland
A9: Transaction Type | B9: Acquistion
A10: Selected Standalone Equity Value | B10: =Valuation!C125 -> 336.40024
A11: Acquisition Premium | B11: 0.15 | C11: Assume base case 15% to provide a meaningful but not excessive premium
A12: Equity Purchase Price | B12: =B10*(1+B11) -> 386.86027
A13: Target Net Debt | B13: ='Poundland Operating Model'!F20 -> 47.459
A14: Transaction Enterprise Value | B14: =B12+B13 -> 434.31927
A15: Transaction Fee | B15: =0.01*B12 -> 3.8686027 | C15: Assume 1% of purchase price
A16: Total Deal Cost | B16: =B14+B15 -> 438.18787
A20: Acquisition Price Analysis
A21: Acquisition Premium | B21: 0 | C21: 0.05 | D21: 0.1 | E21: 0.15 | F21: 0.2 | G21: 0.25 | H21: 0.3
A22: Standalone Equity Value | B22: =B10 -> 336.40024 | C22: =B10 -> 336.40024 | D22: =B10 -> 336.40024 | E22: =B10 -> 336.40024 | F22: =B10 -> 336.40024 | G22: =B10 -> 336.40024 | H22: =B10 -> 336.40024
A23: Equity Purchase Price | B23: =B22*(1+B21) -> 336.40024 | C23: =C22*(1+C21) -> 353.22025 | D23: =D22*(1+D21) -> 370.04026 | E23: =E22*(1+E21) -> 386.86027 | F23: =F22*(1+F21) -> 403.68028 | G23: =G22*(1+G21) -> 420.5003 | H23: =H22*(1+H21) -> 437.32031
A24: Target Net Debt | B24: =B13 -> 47.459 | C24: =B13 -> 47.459 | D24: =B13 -> 47.459 | E24: =B13 -> 47.459 | F24: =B13 -> 47.459 | G24: =B13 -> 47.459 | H24: =B13 -> 47.459
A25: Transaction EV | B25: =B23+B24 -> 383.85924 | C25: =C23+C24 -> 400.67925 | D25: =D23+D24 -> 417.49926 | E25: =E23+E24 -> 434.31927 | F25: =F23+F24 -> 451.13928 | G25: =G23+G24 -> 467.9593 | H25: =H23+H24 -> 484.77931
A26: Transaction Fees | B26: =0.01*B23 -> 3.3640024 | C26: =0.01*C23 -> 3.5322025 | D26: =0.01*D23 -> 3.7004026 | E26: =0.01*E23 -> 3.8686027 | F26: =0.01*F23 -> 4.0368028 | G26: =0.01*G23 -> 4.205003 | H26: =0.01*H23 -> 4.3732031
A27: Total Deal Cost | B27: =B25+B26 -> 387.22324 | C27: =C25+C26 -> 404.21145 | D27: =D25+D26 -> 421.19966 | E27: =E25+E26 -> 438.18787 | F27: =F25+F26 -> 455.17609 | G27: =G25+G26 -> 472.1643 | H27: =H25+H26 -> 489.15251
A28: EV / Revenue FY26E | B28: =B25/'Poundland Operating Model'!K15 -> 0.26084139 | C28: =C25/'Poundland Operating Model'!K15 -> 0.27227098 | D28: =D25/'Poundland Operating Model'!K15 -> 0.28370058 | E28: =E25/'Poundland Operating Model'!K15 -> 0.29513017 | F28: =F25/'Poundland Operating Model'!K15 -> 0.30655977 | G28: =G25/'Poundland Operating Model'!K15 -> 0.31798936 | H28: =H25/'Poundland Operating Model'!K15 -> 0.32941895
A29: EV / EBITDA FY26E | B29: =B25/'Poundland Operating Model'!K17 -> 7.4526111 | C29: =C25/'Poundland Operating Model'!K17 -> 7.779171 | D29: =D25/'Poundland Operating Model'!K17 -> 8.1057308 | E29: =E25/'Poundland Operating Model'!K17 -> 8.4322906 | F29: =F25/'Poundland Operating Model'!K17 -> 8.7588505 | G29: =G25/'Poundland Operating Model'!K17 -> 9.0854103 | H29: =H25/'Poundland Operating Model'!K17 -> 9.4119701
A33: Financing
A34: Financing Assumptions | B34: Value | C34: Explanation
A35: Cash Consideration % | B35: 0.5 | C35: Balanced 50/50
A36: Debt Consideration % | B36: =1-B35 -> 0.5 | C36: Remaining after cash
A37: Share Consideration % | B37: 0 | C37: No equity issuance in base case, share financing tested separately in sensitivity analysis
A38: Total Financing % | B38: =SUM(B35:B37) -> 1
A39: Interest Rate on New Debt | B39: =Valuation!B14 -> 0.0667 | C39: Use B&M's existing implied pre-tax cost of debt from DCF
A40: Financing Fee % | B40: 0.01 | C40: Assume 1% of new acquisition debt
A42: Financing Calculation | B42: Value
A43: Cash Consideration | B43: =B16*B35 -> 219.09394
A44: New Acquisition Debt | B44: =B16*B36 -> 219.09394
A45: Share Consideration | B45: =B16*B37 -> 0
A46: Shares Issued | B46: =B37/Valuation!B75 -> 0
A47: Incremental Interest Expense | B47: =B44*B39 -> 14.613566
A48: Financing Fees | B48: =B44*B40 -> 2.1909394
A50: Pro Forma Capital Structure | B50: B&M FY26A | C50: Pro Forma
A51: Cash | B51: 342 | C51: =B51-B43 -> 122.90606
A52: Total Debt | B52: 998 | C52: =B52+B44 -> 1217.0939
A53: Net Debt | B53: =B52-B51 -> 656 | C53: =C52-C51 -> 1094.1879
A54: EBITDA | B54: =374+297 -> 671 | C54: =B54+'Poundland Operating Model'!F9 -> 693.93
A55: Net Debt / EBITDA | B55: =B53/B54 -> 0.97764531 | C55: =C53/C54 -> 1.5767986
A59: M&A Analysis Value Creation | B59: Value
A60: Standalone Poundland Equity Value | B60: =Valuation!C125 -> 336.40024
A61: Purchase Price | B61: =B12 -> 386.86027
A62: Transaction EV | B62: =B14 -> 434.31927
A63: PV of Revenue Synergies | B63: =('Synergies and Integration'!B56/(1+Valuation!B19)^1)+('Synergies and Integration'!C56/(1+Valuation!B19)^2)+('Synergies and Integration'!D56/(1+Valuation!B19)^3)+('Synergies and Integration'!E56/(1+Valuation!B19)^4)+('Synergies and Integration'!F56/(1+Valuation!B19)^5) -> 28.741781
A64: PV of Cost Synergies | B64: =('Synergies and Integration'!B57/(1+Valuation!B19)^1)+('Synergies and Integration'!C57/(1+Valuation!B19)^2)+('Synergies and Integration'!D57/(1+Valuation!B19)^3)+('Synergies and Integration'!E57/(1+Valuation!B19)^4)+('Synergies and Integration'!F57/(1+Valuation!B19)^5) -> 88.326133
A65: PV of Integration Costs | B65: =('Synergies and Integration'!B59/(1+Valuation!B19)^1)+('Synergies and Integration'!C59/(1+Valuation!B19)^2)+('Synergies and Integration'!D59/(1+Valuation!B19)^3)+('Synergies and Integration'!E59/(1+Valuation!B19)^4)+('Synergies and Integration'!F59/(1+Valuation!B19)^5) -> 43.685612
A66: PV of Transaction/Financing Costs | B66: =(B15+B48)/(1+Valuation!B19) -> 5.5743645
A67: NPV of Acquisition Benefits | B67: =B63+B64-B65-B66 -> 67.807938
A68: Value Creation / (Destruction) | B68: =B60+B67-B61 -> 17.347903
A69: Value Creation / Purchase Price | B69: =B68/B61 -> 0.044842812
A71: EPS: Incremental earnings to cover acquistion financing | B71: ='Accretion & Dilution'!D76+(1-Valuation!B10)*'Synergies and Integration'!D60 -> 20.297673
A72: EPS: After tax csot of debt | B72: =(B36*Valuation!B14*(1-Valuation!B10)) -> 0.0250125
A73: EPS: Maximum Total Deal Cost | B73: =B71/B72 -> 811.50118
A75: Maximum Price Analysis | B75: Value
A76: Maximum Value-Creating Purchase Price | B76: =B60+B67 -> 404.20817
A77: Maximum Acquisition Premium | B77: =B76/B60-1 -> 0.20156923
A78: Maximum EPS-Neutral Purchase Price | B78: =(B73-B13)/1.01 -> 756.47741
A79: Maximum EPS-Neutral Acquisition Premium | B79: =B78/B60-1 -> 1.2487422
A80: Proposed Purchase Price | B80: =B12 -> 386.86027
A81: Purchase Price Headroom / (Shortfall) | B81: =B76-B80 -> 17.347903

Sheet Synergies and Integration
A1: Synergies and Integration
A3: Driver | B3: FY26E | C3: FY27E | D3: FY28E | E3: FY29E | F3: FY30E | G3: Explanation / Assumption
A5: Revenue Synergies
A6: Cross-selling / Basket size | B6: =0.005*'Poundland Operating Model'!K15 -> 7.3580967 | C6: =0.01*'Poundland Operating Model'!L15 -> 14.936936 | D6: =0.015*'Poundland Operating Model'!M15 -> 22.96554 | E6: =0.02*'Poundland Operating Model'!N15 -> 31.692445 | F6: =0.02*'Poundland Operating Model'!O15 -> 32.80168 | G6: Use 0.5, 1, 1.5, 2, 2 % of Poundland revenue, increase with integration
A7: Channel / Estate Optimisation | B7: =0*'Poundland Operating Model'!K15 -> 0 | C7: =0.005*'Poundland Operating Model'!L15 -> 7.4684682 | D7: =0.01*'Poundland Operating Model'!M15 -> 15.31036 | E7: =0.015*'Poundland Operating Model'!N15 -> 23.769334 | F7: =0.015*'Poundland Operating Model'!O15 -> 24.60126 | G7: Use 0, 0.5, 1, 1.5, 1.5 increases as B&M's channels and locations are utilised
A8: Customer Base Optimisation | B8: =0*'Poundland Operating Model'!K15 -> 0 | C8: =0.0025*'Poundland Operating Model'!L15 -> 3.7342341 | D8: =0.005*'Poundland Operating Model'!M15 -> 7.6551799 | E8: =0.0075*'Poundland Operating Model'!N15 -> 11.884667 | F8: =0.01*'Poundland Operating Model'!O15 -> 16.40084 | G8: Use 0, 0.25, 0.5, 0.75, 1 as customer data and marketing integration improve
A9: Total Revenue Synergies | B9: =SUM(B6:B8) -> 7.3580967 | C9: =SUM(C6:C8) -> 26.139639 | D9: =SUM(D6:D8) -> 45.931079 | E9: =SUM(E6:E8) -> 67.346445 | F9: =SUM(F6:F8) -> 73.803781 | G9: Formula
A10: Revenue Synergy % of Poundland Revenue | B10: =B9/'Poundland Operating Model'!K15 -> 0.005 | C10: =C9/'Poundland Operating Model'!L15 -> 0.0175 | D10: =D9/'Poundland Operating Model'!M15 -> 0.03 | E10: =E9/'Poundland Operating Model'!N15 -> 0.0425 | F10: =F9/'Poundland Operating Model'!O15 -> 0.045 | G10: Formula
A11: Realisation % | B11: 0.5 | C11: 0.7 | D11: 0.85 | E11: 0.95 | F11: 1 | G11: Synergies progressively realised and complete by FY30
A12: Gross Revenue Synergies | B12: =B9*B11 -> 3.6790484 | C12: =C9*C11 -> 18.297747 | D12: =D9*D11 -> 39.041418 | E12: =E9*E11 -> 63.979123 | F12: =F9*F11 -> 73.803781 | G12: Formula
A13: Incremental Gross Profit | B13: =0.3*B12 -> 1.1037145 | C13: =0.3*C12 -> 5.4893241 | D13: =0.3*D12 -> 11.712425 | E13: =0.3*E12 -> 19.193737 | F13: =0.3*F12 -> 22.141134 | G13: Assume 30% incremental gross margin consistent with Poundlands implied
A14: Incremental EBITDA | B14: =0.2*B12 -> 0.73580968 | C14: =0.2*C12 -> 3.6595494 | D14: =0.2*D12 -> 7.8082835 | E14: =0.2*E12 -> 12.795825 | F14: =0.2*F12 -> 14.760756 | G14: Assume 20% incremental EBITDA margin after operating costs
A16: Cost Synergies
A17: Procurement | B17: =0.005*'Poundland Operating Model'!K15 -> 7.3580967 | C17: =0.0065*'Poundland Operating Model'!L15 -> 9.7090087 | D17: =0.008*'Poundland Operating Model'!M15 -> 12.248288 | E17: =0.01*'Poundland Operating Model'!N15 -> 15.846222 | F17: =0.0125*'Poundland Operating Model'!O15 -> 20.50105 | G17: Procurement savings from B&M greater purchasing scale etc so use 0.5, 0.65, 0.8, 1, 1.25%
A18: Distribution | B18: =0.001*'Poundland Operating Model'!K15 -> 1.4716193 | C18: =0.002*'Poundland Operating Model'!L15 -> 2.9873873 | D18: =0.003*'Poundland Operating Model'!M15 -> 4.5931079 | E18: =0.004*'Poundland Operating Model'!N15 -> 6.338489 | F18: =0.005*'Poundland Operating Model'!O15 -> 8.2004201 | G18: Distribution savings from network optimisation etc so use 0.1, 0.2, 0.3, 0.4, 0.5 %
A19: Head Office | B19: =0.003*'Poundland Operating Model'!K15 -> 4.4148581 | C19: =0.004*'Poundland Operating Model'!L15 -> 5.9747746 | D19: =0.005*'Poundland Operating Model'!M15 -> 7.6551799 | E19: =0.006*'Poundland Operating Model'!N15 -> 9.5077334 | F19: =0.007*'Poundland Operating Model'!O15 -> 11.480588 | G19: Savings from removing duplicate corporate functions so use 0.3, 0.4, 0.5, 0.6, 0.7 % of Poundland Revenue
A20: Technology | B20: =0.001*'Poundland Operating Model'!K15 -> 1.4716193 | C20: =0.0015*'Poundland Operating Model'!L15 -> 2.2405405 | D20: =0.0015*'Poundland Operating Model'!M15 -> 2.296554 | E20: =0.002*'Poundland Operating Model'!N15 -> 3.1692445 | F20: =0.002*'Poundland Operating Model'!O15 -> 3.280168 | G20: Savings from combining software licenses, IT infrastructure so use 0.1, 0.15, 0.15, 0.2, 0.2 %
A21: Marketing | B21: =0.001*'Poundland Operating Model'!K15 -> 1.4716193 | C21: =0.0015*'Poundland Operating Model'!L15 -> 2.2405405 | D21: =0.0015*'Poundland Operating Model'!M15 -> 2.296554 | E21: =0.002*'Poundland Operating Model'!N15 -> 3.1692445 | F21: =0.002*'Poundland Operating Model'!O15 -> 3.280168 | G21: Savings from marketing by combining campaigns etc. so use 0.1, 0.15, 0.15, 0.2, 0.2 %
A22: Store rationalisation | B22: =B38 -> -6.7920893 | C22: =C38 -> -5.3346201 | D22: =D38 -> -3.7342341 | E22: =E38 -> 0 | F22: =F38 -> 0 | G22: Linked to Net EBITDA Impact below
A23: Total Cost Synergies | B23: =SUM(B17:B22) -> 9.3957235 | C23: =SUM(C17:C22) -> 17.817631 | D23: =SUM(D17:D22) -> 25.35545 | E23: =SUM(E17:E22) -> 38.030934 | F23: =SUM(F17:F22) -> 46.742395 | G23: Formula
A24: % of Poundland Revenue | B24: =B23/'Poundland Operating Model'!K15 -> 0.0063846154 | C24: =C23/'Poundland Operating Model'!L15 -> 0.011928571 | D24: =D23/'Poundland Operating Model'!M15 -> 0.016560976 | E24: =E23/'Poundland Operating Model'!N15 -> 0.024 | F24: =F23/'Poundland Operating Model'!O15 -> 0.0285 | G24: Formula
A25: Realisation % | B25: 0.5 | C25: 0.7 | D25: 0.85 | E25: 0.95 | F25: 1 | G25: Same as revenue synergies
A26: Gross Cost Synergies | B26: =B23*B25 -> 4.6978618 | C26: =C23*C25 -> 12.472342 | D26: =D23*D25 -> 21.552132 | E26: =E23*E25 -> 36.129387 | F26: =F23*F25 -> 46.742395 | G26: Formula
A28: Store Rationalisation
A29: Opening stores | B29: 650 | C29: =B29-B30 -> 630 | D29: =C29-C30 -> 615 | E29: =D29-D30 -> 605 | F29: =E29-E30 -> 605 | G29: Assume acquistion accelerates rationalisation of weakest locations
A30: Stores closed | B30: 20 | C30: 15 | D30: 10 | E30: 0 | F30: 0 | G30: Assume 45 underperforming stores close over next 5 years
A31: Remaining stores | B31: =B29-B30 -> 630 | C31: =C29-C30 -> 615 | D31: =D29-D30 -> 605 | E31: =E29-E30 -> 605 | F31: =F29-F30 -> 605 | G31: Formula
A32: Revenue/store | B32: ='Poundland Operating Model'!K15/B29 -> 2.2640298 | C32: ='Poundland Operating Model'!L15/C29 -> 2.3709423 | D32: ='Poundland Operating Model'!M15/D29 -> 2.4894894 | E32: ='Poundland Operating Model'!N15/E29 -> 2.6192103 | F32: ='Poundland Operating Model'!O15/F29 -> 2.7108827 | G32: Formula
A33: Revenue lost | B33: =B30*B32 -> 45.280595 | C33: =C30*C32 -> 35.564134 | D33: =D30*D32 -> 24.894894 | E33: =E30*E32 -> 0 | F33: =F30*F32 -> 0 | G33: Formula
A34: Rent savings | B34: =0.25*B33 -> 11.320149 | C34: =0.25*C33 -> 8.8910336 | D34: =0.25*D33 -> 6.2237235 | E34: =0.25*E33 -> 0 | F34: =0.25*F33 -> 0 | G34: Assume 25%
A35: Labour savings | B35: =0.25*B33 -> 11.320149 | C35: =0.25*C33 -> 8.8910336 | D35: =0.25*D33 -> 6.2237235 | E35: =0.25*E33 -> 0 | F35: =0.25*F33 -> 0 | G35: Assume 25%
A36: Other savings | B36: =0.35*B33 -> 15.848208 | C36: =0.35*C33 -> 12.447447 | D36: =0.35*D33 -> 8.7132129 | E36: =0.35*E33 -> 0 | F36: =0.35*F33 -> 0 | G36: Assume 35%
A37: Total savings | B37: =SUM(B34:B36) -> 38.488506 | C37: =SUM(C34:C36) -> 30.229514 | D37: =SUM(D34:D36) -> 21.16066 | E37: =SUM(E34:E36) -> 0 | F37: =SUM(F34:F36) -> 0 | G37: Formula
A38: Net EBITDA impact | B38: =B37-B33 -> -6.7920893 | C38: =C37-C33 -> -5.3346201 | D38: =D37-D33 -> -3.7342341 | E38: =E37-E33 -> 0 | F38: =F37-F33 -> 0 | G38: Formula
A40: Integration Costs
A41: Redundancies | B41: 4 | C41: 3 | D41: 2 | E41: 0 | F41: 0 | G41: £9m total costs spread over 3 years after restructuring
A42: IT Integration | B42: 5 | C42: 4 | D42: 3 | E42: 0 | F42: 0 | G42: £12m total IT integration expenditure
A43: Rebranding | B43: 2.5 | C43: 1.5 | D43: 1 | E43: 0 | F43: 0 | G43: £5m total rebranding costs
A44: Store Closures | B44: =0.1*B30 -> 2 | C44: =0.1*C30 -> 1.5 | D44: =0.1*D30 -> 1 | E44: =0.1*E30 -> 0 | F44: =0.1*F30 -> 0 | G44: Assume £100k per closure
A45: Consultancy / Professional Fees | B45: 3 | C45: 2 | D45: 1 | E45: 0 | F45: 0 | G45: £6m total professional and integration advisory costs
A46: Systems Integration | B46: 3 | C46: 2 | D46: 1 | E46: 0 | F46: 0 | G46: £6m total expenditure to integrate finance, reporting, and systems
A47: Inventory / Write-downs | B47: 2.5 | C47: 1.5 | D47: 1 | E47: 0 | F47: 0 | G47: £5m total inventory related costs from clearance and write downs
A48: Other | B48: 1 | C48: 1 | D48: 1 | E48: 0 | F48: 0 | G48: £3m contingency for miscellaneous integration costs
A49: Total Integration Costs | B49: =SUM(B41:B48) -> 23 | C49: =SUM(C41:C48) -> 16.5 | D49: =SUM(D41:D48) -> 11 | E49: =SUM(E41:E48) -> 0 | F49: =SUM(F41:F48) -> 0 | G49: Formula
A50: Cumulative Integration Costs | B50: =SUM(B49) -> 23 | C50: =SUM(B49:C49) -> 39.5 | D50: =SUM(B49:D49) -> 50.5 | E50: =SUM(B49:E49) -> 50.5 | F50: =SUM(B49:F49) -> 50.5 | G50: Formula
A54: Synergy Summary
B55: FY26E | C55: FY27E | D55: FY28E | E55: FY29E | F55: FY30E
A56: Revenue Synergies | B56: =1*B14 -> 0.73580968 | C56: =1*C14 -> 3.6595494 | D56: =1*D14 -> 7.8082835 | E56: =1*E14 -> 12.795825 | F56: =1*F14 -> 14.760756
A57: Cost Synergies | B57: =1*B26 -> 4.6978618 | C57: =1*C26 -> 12.472342 | D57: =1*D26 -> 21.552132 | E57: =1*E26 -> 36.129387 | F57: =1*F26 -> 46.742395
A58: Total EBITDA Synergies | B58: =B56+B57 -> 5.4336714 | C58: =C56+C57 -> 16.131891 | D58: =D56+D57 -> 29.360416 | E58: =E56+E57 -> 48.925212 | F58: =F56+F57 -> 61.503151
A59: Integration Costs | B59: =B49 -> 23 | C59: =C49 -> 16.5 | D59: =D49 -> 11 | E59: =E49 -> 0 | F59: =F49 -> 0
A60: Net EBITDA Benefit | B60: =B58-B59 -> -17.566329 | C60: =C58-C59 -> -0.36810869 | D60: =D58-D59 -> 18.360416 | E60: =E58-E59 -> 48.925212 | F60: =F58-F59 -> 61.503151

Sheet Accretion & Dilution
A1: Accretion & Dilution
A5: Pro Forma Income Statement | B5: FY26E | C5: FY27E | D5: FY28E | E5: FY29E | F5: FY30E
A7: Revenue
A8: B&M Revenue | B8: ='B&M Operating Model'!K15 -> 5765.985 | C8: ='B&M Operating Model'!L15 -> 5967.7945 | D8: ='B&M Operating Model'!M15 -> 6176.6673 | E8: ='B&M Operating Model'!N15 -> 6392.8506 | F8: ='B&M Operating Model'!O15 -> 6616.6004
A9: Poundland Revenue | B9: ='Poundland Operating Model'!K15 -> 1471.6193 | C9: ='Poundland Operating Model'!L15 -> 1493.6936 | D9: ='Poundland Operating Model'!M15 -> 1531.036 | E9: ='Poundland Operating Model'!N15 -> 1584.6222 | F9: ='Poundland Operating Model'!O15 -> 1640.084
A10: Revenue Synergies | B10: ='Synergies and Integration'!B12 -> 3.6790484 | C10: ='Synergies and Integration'!C12 -> 18.297747 | D10: ='Synergies and Integration'!D12 -> 39.041418 | E10: ='Synergies and Integration'!E12 -> 63.979123 | F10: ='Synergies and Integration'!F12 -> 73.803781
A11: Pro Forma Revenue | B11: =B8+B9+B10 -> 7241.2834 | C11: =C8+C9+C10 -> 7479.7859 | D11: =D8+D9+D10 -> 7746.7447 | E11: =E8+E9+E10 -> 8041.452 | F11: =F8+F9+F10 -> 8330.4882
A12: Revenue Growth | B12: =B11/'B&M Operating Model'!F7-1 -> 0.29981752 | C12: =C11/B11-1 -> 0.032936491 | D12: =D11/C11-1 -> 0.035690703 | E12: =E11/D11-1 -> 0.03804273 | F12: =F11/E11-1 -> 0.035943286
A14: EBITDA
A15: B&M EBITDA | B15: ='B&M Operating Model'!K17 -> 778.40797 | C15: ='B&M Operating Model'!L17 -> 745.97431 | D15: ='B&M Operating Model'!M17 -> 725.75841 | E15: ='B&M Operating Model'!N17 -> 687.23144 | F15: ='B&M Operating Model'!O17 -> 651.73514
A16: Poundland EBITDA | B16: ='Poundland Operating Model'!K17 -> 51.506677 | C16: ='Poundland Operating Model'!L17 -> 59.747746 | D16: ='Poundland Operating Model'!M17 -> 76.551799 | E16: ='Poundland Operating Model'!N17 -> 103.00045 | F16: ='Poundland Operating Model'!O17 -> 106.60546
A17: Revenue Synergy EBITDA | B17: ='Synergies and Integration'!B56 -> 0.73580968 | C17: ='Synergies and Integration'!C56 -> 3.6595494 | D17: ='Synergies and Integration'!D56 -> 7.8082835 | E17: ='Synergies and Integration'!E56 -> 12.795825 | F17: ='Synergies and Integration'!F56 -> 14.760756
A18: Cost Synergies | B18: ='Synergies and Integration'!B57 -> 4.6978618 | C18: ='Synergies and Integration'!C57 -> 12.472342 | D18: ='Synergies and Integration'!D57 -> 21.552132 | E18: ='Synergies and Integration'!E57 -> 36.129387 | F18: ='Synergies and Integration'!F57 -> 46.742395
A19: Pro Forma EBITDA | B19: =SUM(B15:B18) -> 835.34832 | C19: =SUM(C15:C18) -> 821.85395 | D19: =SUM(D15:D18) -> 831.67062 | E19: =SUM(E15:E18) -> 839.1571 | F19: =SUM(F15:F18) -> 819.84375
A21: EBIT
A22: D&A | B22: ='B&M Operating Model'!K19+'Poundland Operating Model'!K19 -> 345.87314 | C22: ='B&M Operating Model'!L19+'Poundland Operating Model'!L19 -> 350.68296 | D22: ='B&M Operating Model'!M19+'Poundland Operating Model'!M19 -> 356.16417 | E22: ='B&M Operating Model'!N19+'Poundland Operating Model'!N19 -> 363.84887 | F22: ='B&M Operating Model'!O19+'Poundland Operating Model'!O19 -> 373.27528
A23: Pro Forma EBIT | B23: =B19-B22 -> 489.47518 | C23: =C19-C22 -> 471.17098 | D23: =D19-D22 -> 475.50645 | E23: =E19-E22 -> 475.30823 | F23: =F19-F22 -> 446.56847
A24: EBIT Margin | B24: =B23/B11 -> 0.067595087 | C24: =C23/C11 -> 0.062992577 | D24: =D23/D11 -> 0.061381454 | E24: =E23/E11 -> 0.059107265 | F24: =F23/F11 -> 0.053606519
A26: Net Income
A27: Operating EBIT | B27: =B23 -> 489.47518 | C27: =C23 -> 471.17098 | D27: =D23 -> 475.50645 | E27: =E23 -> 475.30823 | F27: =F23 -> 446.56847
A28: Interest | B28: =(Valuation!B14*'B&M Operating Model'!F18)+(Valuation!K15*'Poundland Operating Model'!F18)+'M&A Analysis'!B47 -> 96.261341 | C28: =(Valuation!B14*'B&M Operating Model'!F18)+(Valuation!K15*'Poundland Operating Model'!F18)+'M&A Analysis'!B47 -> 96.261341 | D28: =(Valuation!B14*'B&M Operating Model'!F18)+(Valuation!K15*'Poundland Operating Model'!F18)+'M&A Analysis'!B47 -> 96.261341 | E28: =(Valuation!B14*'B&M Operating Model'!F18)+(Valuation!K15*'Poundland Operating Model'!F18)+'M&A Analysis'!B47 -> 96.261341 | F28: =(Valuation!B14*'B&M Operating Model'!F18)+(Valuation!K15*'Poundland Operating Model'!F18)+'M&A Analysis'!B47 -> 96.261341
A29: PBT | B29: =B27-B28 -> 393.21384 | C29: =C27-C28 -> 374.90964 | D29: =D27-D28 -> 379.24511 | E29: =E27-E28 -> 379.04689 | F29: =F27-F28 -> 350.30713
A30: Tax | B30: =Valuation!B10*B29 -> 98.30346 | C30: =Valuation!B10*C29 -> 93.727411 | D30: =Valuation!B10*D29 -> 94.811277 | E30: =Valuation!B10*E29 -> 94.761723 | F30: =Valuation!B10*F29 -> 87.576783
A31: Pro Forma Net Income | B31: =B29-B30 -> 294.91038 | C31: =C29-C30 -> 281.18223 | D31: =D29-D30 -> 284.43383 | E31: =E29-E30 -> 284.28517 | F31: =F29-F30 -> 262.73035
A32: Net Income Margin | B32: =B31/B11 -> 0.040726259 | C32: =C31/C11 -> 0.037592284 | D32: =D31/D11 -> 0.036716562 | E32: =E31/E11 -> 0.035352467 | F32: =F31/F11 -> 0.03153841
A36: Pro Forma Free Cash Flow | B36: FY26E | C36: FY27E | D36: FY28E | E36: FY29E | F36: FY30E
A37: Pro Forma EBIT | B37: =B23 -> 489.47518 | C37: =C23 -> 471.17098 | D37: =D23 -> 475.50645 | E37: =E23 -> 475.30823 | F37: =F23 -> 446.56847
A38: Tax | B38: =Valuation!B10*B37 -> 122.3688 | C38: =Valuation!B10*C37 -> 117.79275 | D38: =Valuation!B10*D37 -> 118.87661 | E38: =Valuation!B10*E37 -> 118.82706 | F38: =Valuation!B10*F37 -> 111.64212
A39: NOPAT | B39: =B37-B38 -> 367.10639 | C39: =C37-C38 -> 353.37824 | D39: =D37-D38 -> 356.62984 | E39: =E37-E38 -> 356.48117 | F39: =F37-F38 -> 334.92635
A40: D&A | B40: =B22 -> 345.87314 | C40: =C22 -> 350.68296 | D40: =D22 -> 356.16417 | E40: =E22 -> 363.84887 | F40: =F22 -> 373.27528
A41: Capex | B41: ='B&M Operating Model'!K28+'Poundland Operating Model'!K28 -> 181.95562 | C41: ='B&M Operating Model'!L28+'Poundland Operating Model'!L28 -> 197.59333 | D41: ='B&M Operating Model'!M28+'Poundland Operating Model'!M28 -> 212.00464 | E41: ='B&M Operating Model'!N28+'Poundland Operating Model'!N28 -> 227.70833 | F41: ='B&M Operating Model'!O28+'Poundland Operating Model'!O28 -> 244.25157
A42: Change in NWC | B42: ='B&M Operating Model'!K31+'Poundland Operating Model'!K31 -> 4.789713 | C42: ='B&M Operating Model'!L31+'Poundland Operating Model'!L31 -> 11.667083 | D42: ='B&M Operating Model'!M31+'Poundland Operating Model'!M31 -> 11.785522 | E42: ='B&M Operating Model'!N31+'Poundland Operating Model'!N31 -> 11.899276 | F42: ='B&M Operating Model'!O31+'Poundland Operating Model'!O31 -> 12.315751
A43: Operating FCF | B43: =B39+B40-B41-B42 -> 526.23419 | C43: =C39+C40-C41-C42 -> 494.80079 | D43: =D39+D40-D41-D42 -> 489.00384 | E43: =E39+E40-E41-E42 -> 480.72244 | F43: =F39+F40-F41-F42 -> 451.63431
A44: Integration Costs | B44: ='Synergies and Integration'!B49 -> 23 | C44: ='Synergies and Integration'!C49 -> 16.5 | D44: ='Synergies and Integration'!D49 -> 11 | E44: ='Synergies and Integration'!E49 -> 0 | F44: ='Synergies and Integration'!F49 -> 0
A45: Transaction/Financing Costs | B45: ='M&A Analysis'!B15+'M&A Analysis'!B48 -> 6.0595421 | C45: 0 | D45: 0 | E45: 0 | F45: 0
A46: Pro Forma FCF | B46: =B43-B44-B45 -> 497.17465 | C46: =C43-C44-C45 -> 478.30079 | D46: =D43-D44-D45 -> 478.00384 | E46: =E43-E44-E45 -> 480.72244 | F46: =F43-F44-F45 -> 451.63431
A47: FCF Margin | B47: =B46/B11 -> 0.068658361 | C47: =C46/C11 -> 0.063945786 | D47: =D46/D11 -> 0.061703833 | E47: =E46/E11 -> 0.059780551 | F47: =F46/F11 -> 0.054214627
A48: Incremental FCF vs B&M | B48: =B46-Valuation!B32 -> -16.777756 | C48: =C46-Valuation!C32 -> 6.1228364 | D48: =D46-Valuation!D32 -> 29.756831 | E48: =E46-Valuation!E32 -> 70.646545 | F48: =F46-Valuation!F32 -> 77.988174
A49: Cumulative Incremental FCF | B49: =SUM(B48) -> -16.777756 | C49: =SUM(B48:C48) -> -10.65492 | D49: =SUM(B48:D48) -> 19.101911 | E49: =SUM(B48:E48) -> 89.748457 | F49: =SUM(B48:F48) -> 167.73663
A53: Acquistion Impact
A54: Forecast Years | B54: FY26E | C54: FY27E | D54: FY28E | E54: FY29E | F54: FY30E
A55: B&M Standalone Revenue | B55: ='B&M Operating Model'!K15 -> 5765.985 | C55: ='B&M Operating Model'!L15 -> 5967.7945 | D55: ='B&M Operating Model'!M15 -> 6176.6673 | E55: ='B&M Operating Model'!N15 -> 6392.8506 | F55: ='B&M Operating Model'!O15 -> 6616.6004
A56: Pro Forma Revenue | B56: =B11 -> 7241.2834 | C56: =C11 -> 7479.7859 | D56: =D11 -> 7746.7447 | E56: =E11 -> 8041.452 | F56: =F11 -> 8330.4882
A57: Revenue Increase % | B57: =B56/B55-1 -> 0.25586234 | C57: =C56/C55-1 -> 0.25335849 | D57: =D56/D55-1 -> 0.25419491 | E57: =E56/E55-1 -> 0.25788204 | F57: =F56/F55-1 -> 0.25902846
A59: B&M Standalone EBITDA | B59: ='B&M Operating Model'!K17 -> 778.40797 | C59: ='B&M Operating Model'!L17 -> 745.97431 | D59: ='B&M Operating Model'!M17 -> 725.75841 | E59: ='B&M Operating Model'!N17 -> 687.23144 | F59: ='B&M Operating Model'!O17 -> 651.73514
A60: Pro Forma EBITDA | B60: =B19 -> 835.34832 | C60: =C19 -> 821.85395 | D60: =D19 -> 831.67062 | E60: =E19 -> 839.1571 | F60: =F19 -> 819.84375
A61: EBITDA Increase % | B61: =B60/B59-1 -> 0.07314975 | C61: =C60/C59-1 -> 0.10171883 | D61: =D60/D59-1 -> 0.14593316 | E61: =E60/E59-1 -> 0.22106913 | F61: =F60/F59-1 -> 0.25794008
A63: B&M Standalone FCF | B63: =Valuation!B32 -> 513.95241 | C63: =Valuation!C32 -> 472.17795 | D63: =Valuation!D32 -> 448.24701 | E63: =Valuation!E32 -> 410.07589 | F63: =Valuation!F32 -> 373.64614
A64: Pro Forma FCF | B64: =B46 -> 497.17465 | C64: =C46 -> 478.30079 | D64: =D46 -> 478.00384 | E64: =E46 -> 480.72244 | F64: =F46 -> 451.63431
A65: Incremental FCF | B65: =B64-B63 -> -16.777756 | C65: =C64-C63 -> 6.1228364 | D65: =D64-D63 -> 29.756831 | E65: =E64-E63 -> 70.646545 | F65: =F64-F63 -> 77.988174
A67: B&M Standalone Net Debt / EBITDA | B67: ='B&M Operating Model'!F20/B59 -> 1.1960309 | C67: ='B&M Operating Model'!F20/C59 -> 1.2480323 | D67: ='B&M Operating Model'!F20/D59 -> 1.282796 | E67: ='B&M Operating Model'!F20/E59 -> 1.354711 | F67: ='B&M Operating Model'!F20/F59 -> 1.4284944
A68: Pro Forma Net Debt / EBITDA | B68: ='M&A Analysis'!C53/B60 -> 1.3098582 | C68: ='M&A Analysis'!C53/C60 -> 1.3313654 | D68: ='M&A Analysis'!C53/D60 -> 1.3156505 | E68: ='M&A Analysis'!C53/E60 -> 1.303913 | F68: ='M&A Analysis'!C53/F60 -> 1.3346298
A69: Leverage Increase | B69: =B68-B67 -> 0.11382732 | C69: =C68-C67 -> 0.083333104 | D69: =D68-D67 -> 0.032854481 | E69: =E68-E67 -> -0.05079798 | F69: =F68-F67 -> -0.093864638
A73: EPS Accretion / Dilution
A74: Forecast Years | B74: FY26E | C74: FY27E | D74: FY28E | E74: FY29E | F74: FY30E
A75: B&M standalone net income | B75: ='B&M Operating Model'!K25 -> 316.63958 | C75: ='B&M Operating Model'!L25 -> 287.21143 | D75: ='B&M Operating Model'!M25 -> 266.84633 | E75: ='B&M Operating Model'!N25 -> 232.6469 | F75: ='B&M Operating Model'!O25 -> 200.61872
A76: Poundland net income | B76: ='Poundland Operating Model'!K25 -> -14.844276 | C76: ='Poundland Operating Model'!L25 -> -7.1679419 | D76: ='Poundland Operating Model'!M25 -> 6.5273616 | E76: ='Poundland Operating Model'!N25 -> 25.904536 | F76: ='Poundland Operating Model'!O25 -> 26.944444
A77: After-tax revenue synergy contribution | B77: ='Synergies and Integration'!B56*(1-Valuation!B10) -> 0.55185726 | C77: ='Synergies and Integration'!C56*(1-Valuation!B10) -> 2.7446621 | D77: ='Synergies and Integration'!D56*(1-Valuation!B10) -> 5.8562126 | E77: ='Synergies and Integration'!E56*(1-Valuation!B10) -> 9.5968684 | F77: ='Synergies and Integration'!F56*(1-Valuation!B10) -> 11.070567
A78: After-tax cost synergy contribution | B78: ='Synergies and Integration'!B57*(1-Valuation!B10) -> 3.5233963 | C78: ='Synergies and Integration'!C57*(1-Valuation!B10) -> 9.3542564 | D78: ='Synergies and Integration'!D57*(1-Valuation!B10) -> 16.164099 | E78: ='Synergies and Integration'!E57*(1-Valuation!B10) -> 27.09704 | F78: ='Synergies and Integration'!F57*(1-Valuation!B10) -> 35.056796
A79: After-tax integration costs | B79: ='Synergies and Integration'!B59*(1-Valuation!B10) -> 17.25 | C79: ='Synergies and Integration'!C59*(1-Valuation!B10) -> 12.375 | D79: ='Synergies and Integration'!D59*(1-Valuation!B10) -> 8.25 | E79: ='Synergies and Integration'!E59*(1-Valuation!B10) -> 0 | F79: ='Synergies and Integration'!F59*(1-Valuation!B10) -> 0
A80: Incremental interest | B80: ='M&A Analysis'!B47*(1-Valuation!B10) -> 10.960174 | C80: ='M&A Analysis'!B47*(1-Valuation!B10) -> 10.960174 | D80: ='M&A Analysis'!B47*(1-Valuation!B10) -> 10.960174 | E80: ='M&A Analysis'!B47*(1-Valuation!B10) -> 10.960174 | F80: ='M&A Analysis'!B47*(1-Valuation!B10) -> 10.960174
A81: Pro forma net income | B81: =SUM(B75:B78)-SUM(B79:B80) -> 277.66038 | C81: =SUM(C75:C78)-SUM(C79:C80) -> 268.80723 | D81: =SUM(D75:D78)-SUM(D79:D80) -> 276.18383 | E81: =SUM(E75:E78)-SUM(E79:E80) -> 284.28517 | F81: =SUM(F75:F78)-SUM(F79:F80) -> 262.73035
A83: B&M Existing Shares Outstanding | B83: =Valuation!B76 -> 1005.0383 | C83: =Valuation!B76 -> 1005.0383 | D83: =Valuation!B76 -> 1005.0383 | E83: =Valuation!B76 -> 1005.0383 | F83: =Valuation!B76 -> 1005.0383
A84: Pro Forma Shares Outstanding | B84: =Valuation!B76 -> 1005.0383 | C84: =Valuation!B76 -> 1005.0383 | D84: =Valuation!B76 -> 1005.0383 | E84: =Valuation!B76 -> 1005.0383 | F84: =Valuation!B76 -> 1005.0383
A85: B&M standalone EPS | B85: =B75/B83 -> 0.31505226 | C85: =C75/C83 -> 0.28577164 | D85: =D75/D83 -> 0.26550863 | E85: =E75/E83 -> 0.23148064 | F85: =F75/F83 -> 0.19961301
A86: Pro forma EPS | B86: =B81/B84 -> 0.27626847 | C86: =C81/C84 -> 0.2674597 | D86: =D81/D84 -> 0.27479932 | E86: =E81/E84 -> 0.28286005 | F86: =F81/F84 -> 0.26141328
A87: EPS accretion/(dilution) | B87: =B86-B85 -> -0.038783794 | C87: =C86-C85 -> -0.018311937 | D87: =D86-D85 -> 0.0092906902 | E87: =E86-E85 -> 0.051379408 | F87: =F86-F85 -> 0.061800267
A88: EPS accretion/(dilution) % | B88: =B86/B85-1 -> -0.12310273 | C88: =C86/C85-1 -> -0.064078918 | D88: =D86/D85-1 -> 0.034992046 | E88: =E86/E85-1 -> 0.22195985 | F88: =F86/F85-1 -> 0.30960039
A90: First Year of EPS Accretion | B90: FY28

Sheet Summary & Sensitivities
A1: Summary & Sensitivities
A5: Transaction Summary
A7: Transaction | B7: Value
A8: Acquirer | B8: B&M
A9: Target | B9: Poundland
A10: Purchase Price | B10: ='M&A Analysis'!B80 -> 386.86027
A11: Acquisition Premium | B11: ='M&A Analysis'!B11 -> 0.15
A12: Transaction EV | B12: ='M&A Analysis'!B14 -> 434.31927
A14: Financing
A15: Cash | B15: ='M&A Analysis'!B35 -> 0.5
A16: Debt | B16: ='M&A Analysis'!B36 -> 0.5
A17: Shares | B17: ='M&A Analysis'!B37 -> 0
A18: Pro Forma Net Debt / EBITDA | B18: ='M&A Analysis'!C53 -> 1094.1879
A20: Synergies
A21: Revenue Synergies FY30 | B21: ='Synergies and Integration'!F56 -> 14.760756
A22: Cost Synergies FY30 | B22: ='Synergies and Integration'!F57 -> 46.742395
A23: Integration Costs FY30 Cumulative | B23: ='Synergies and Integration'!F50 -> 50.5
A25: Deal Impact
A26: First Year of EPS Accretion | B26: ='Accretion & Dilution'!B90 -> FY28
A27: FY30E EPS Accretion / Dilution | B27: ='Accretion & Dilution'!F88 -> 0.30960039
A28: FY30E Incremental FCF | B28: ='Accretion & Dilution'!F65 -> 77.988174
A29: Value Creation / Destruction | B29: ='M&A Analysis'!B68 -> 17.347903
A30: Maximum Value-Creating Purchase Price | B30: ='M&A Analysis'!B76 -> 404.20817
A31: Maximum Acquisition Premium | B31: ='M&A Analysis'!B77 -> 0.20156923
A32: Maximum EPS-Neutral Purchase Price | B32: ='M&A Analysis'!B78 -> 756.47741
A33: Purchase Price Headroom | B33: ='M&A Analysis'!B81 -> 17.347903
A37: Standalone Valuation
A38: Poundland | B38: Low | C38: Base | D38: High
A39: DCF Equity Value | B39: =Valuation!B122 -> 243.48262 | C39: =Valuation!C122 -> 325.56384 | D39: =Valuation!D122 -> 472.98002
A40: Comparable Equity Value | B40: =Valuation!B124 -> 285.40086 | C40: =Valuation!C124 -> 347.23664 | D40: =Valuation!D124 -> 409.07241
A41: Blended Equity Value | B41: =Valuation!B125 -> 264.44174 | C41: =Valuation!C125 -> 336.40024 | D41: =Valuation!D125 -> 441.02622
A45: Transaction Valuation | B45: Value
A46: Standalone Equity Value | B46: ='M&A Analysis'!B10 -> 336.40024
A47: Acquisition Premium | B47: ='M&A Analysis'!B11 -> 0.15
A48: Equity Purchase Price | B48: ='M&A Analysis'!B12 -> 386.86027
A49: Target Net Debt | B49: ='M&A Analysis'!B13 -> 47.459
A50: Transaction EV | B50: ='M&A Analysis'!B14 -> 434.31927
A51: EV / FY26E Revenue | B51: =B50/'Poundland Operating Model'!K15 -> 0.29513017
A52: EV / FY26E EBITDA | B52: =B50/'Poundland Operating Model'!K17 -> 8.4322906
A56: Deal Financing | B56: Value
A57: Cash Consideration | B57: ='M&A Analysis'!B43 -> 219.09394
A58: Debt Consideration | B58: ='M&A Analysis'!B44 -> 219.09394
A59: Share Consideration | B59: ='M&A Analysis'!B45 -> 0
A60: New Acquisition Debt | B60: ='M&A Analysis'!B44 -> 219.09394
A61: Incremental Interest Expense | B61: ='M&A Analysis'!B47 -> 14.613566
A62: Financing Fees | B62: ='M&A Analysis'!B48 -> 2.1909394
A63: Pro Forma Net Debt / EBITDA | B63: ='M&A Analysis'!C53/'M&A Analysis'!C54 -> 1.5767986
A64: Pro Forma Cash | B64: ='M&A Analysis'!C51 -> 122.90606
A68: EPS Impact
B69: FY26E | C69: FY27E | D69: FY28E | E69: FY29E | F69: FY30E
A70: B&M Standalone EPS | B70: ='Accretion & Dilution'!B85 -> 0.31505226 | C70: ='Accretion & Dilution'!C85 -> 0.28577164 | D70: ='Accretion & Dilution'!D85 -> 0.26550863 | E70: ='Accretion & Dilution'!E85 -> 0.23148064 | F70: ='Accretion & Dilution'!F85 -> 0.19961301
A71: Pro Forma EPS | B71: ='Accretion & Dilution'!B86 -> 0.27626847 | C71: ='Accretion & Dilution'!C86 -> 0.2674597 | D71: ='Accretion & Dilution'!D86 -> 0.27479932 | E71: ='Accretion & Dilution'!E86 -> 0.28286005 | F71: ='Accretion & Dilution'!F86 -> 0.26141328
A72: EPS Accretion / Dilution | B72: ='Accretion & Dilution'!B87 -> -0.038783794 | C72: ='Accretion & Dilution'!C87 -> -0.018311937 | D72: ='Accretion & Dilution'!D87 -> 0.0092906902 | E72: ='Accretion & Dilution'!E87 -> 0.051379408 | F72: ='Accretion & Dilution'!F87 -> 0.061800267
A73: EPS Accretion / Dilution % | B73: ='Accretion & Dilution'!B88 -> -0.12310273 | C73: ='Accretion & Dilution'!C88 -> -0.064078918 | D73: ='Accretion & Dilution'!D88 -> 0.034992046 | E73: ='Accretion & Dilution'!E88 -> 0.22195985 | F73: ='Accretion & Dilution'!F88 -> 0.30960039
A77: Value Creation | B77: Value
A78: PV of Incremental FCF | B78: =('Accretion & Dilution'!B65/(1+Valuation!B19)^1)+('Accretion & Dilution'!C65/(1+Valuation!B19)^2)+('Accretion & Dilution'!D65/(1+Valuation!B19)^3)+('Accretion & Dilution'!E65/(1+Valuation!B19)^4)+('Accretion & Dilution'!F65/(1+Valuation!B19)^5) -> 114.89045
A79: PV of Revenue Synergies | B79: ='M&A Analysis'!B63 -> 28.741781
A80: PV of Cost Synergies | B80: ='M&A Analysis'!B64 -> 88.326133
A81: PV of Integration Costs | B81: ='M&A Analysis'!B65 -> 43.685612
A82: PV of Transaction / Financing Costs | B82: ='M&A Analysis'!B66 -> 5.5743645
A83: NPV of Acquisition Benefits | B83: ='M&A Analysis'!B67 -> 67.807938
A84: Value Creation / (Destruction) | B84: ='M&A Analysis'!B68 -> 17.347903
A85: Value Creation / Purchase Price | B85: ='M&A Analysis'!B69 -> 0.044842812
A89: Purchase Price Sensitivity
A90: Acquistion Premium | B90: 0 | C90: 0.05 | D90: 0.1 | E90: 0.15 | F90: 0.2 | G90: 0.25 | H90: 0.3
A91: Purchase Price | B91: ='M&A Analysis'!B23 -> 336.40024 | C91: ='M&A Analysis'!C23 -> 353.22025 | D91: ='M&A Analysis'!D23 -> 370.04026 | E91: ='M&A Analysis'!E23 -> 386.86027 | F91: ='M&A Analysis'!F23 -> 403.68028 | G91: ='M&A Analysis'!G23 -> 420.5003 | H91: ='M&A Analysis'!H23 -> 437.32031
A92: EV / EBITDA FY26E | B92: ='M&A Analysis'!B29 -> 7.4526111 | C92: ='M&A Analysis'!C29 -> 7.779171 | D92: ='M&A Analysis'!D29 -> 8.1057308 | E92: ='M&A Analysis'!E29 -> 8.4322906 | F92: ='M&A Analysis'!F29 -> 8.7588505 | G92: ='M&A Analysis'!G29 -> 9.0854103 | H92: ='M&A Analysis'!H29 -> 9.4119701
A93: FY28 EPS Accretion | B93: 0.039769151 | C93: 0.038176783 | D93: 0.036584414 | E93: 0.034992046 | F93: 0.033399678 | G93: 0.031807309 | H93: 0.030214941
A94: Pro Forma Net Debt / EBITDA | B94: 1.5033551 | C94: 1.5278363 | D94: 1.5523175 | E94: 1.5767986 | F94: 1.6012798 | G94: 1.625761 | H94: 1.6502421
A95: Value Creation | B95: 68.506556 | C95: 51.453671 | D95: 34.400787 | E95: 17.347903 | F95: 0.29501813 | G95: -16.757866 | H95: -33.810751
A96: Cumulative Incremental FCF | B96: 168.49605 | C96: 168.24291 | D96: 167.98977 | E96: 167.73663 | F96: 167.48349 | G96: 167.23035 | H96: 166.97721
A100: Synergy Sensitivity
A101: Synergy Sensitivity (% of Base Case) | B101: 0.5 | C101: 0.75 | D101: 1 | E101: 1.25
A102: Revenue Synergies FY30 | B102: =B101*'Synergies and Integration'!F56 -> 7.3803781 | C102: =C101*'Synergies and Integration'!F56 -> 11.070567 | D102: =D101*'Synergies and Integration'!F56 -> 14.760756 | E102: =E101*'Synergies and Integration'!F56 -> 18.450945
A103: Cost Synergies FY30 | B103: =B101*'Synergies and Integration'!F57 -> 23.371197 | C103: =C101*'Synergies and Integration'!F57 -> 35.056796 | D103: =D101*'Synergies and Integration'!F57 -> 46.742395 | E103: =E101*'Synergies and Integration'!F57 -> 58.427993
A104: Total Synergies FY30 | B104: =B102+B103 -> 30.751575 | C104: =C102+C103 -> 46.127363 | D104: =D102+D103 -> 61.503151 | E104: =E102+E103 -> 76.878938
A105: EPS Accretion / Dilution FY28 | B105: -0.0062682395 | C105: 0.014361903 | D105: 0.034992046 | E105: 0.055622189
A106: Pro Forma Net Debt / EBITDA | B106: =B63 -> 1.5767986 | C106: =B63 -> 1.5767986 | D106: =B63 -> 1.5767986 | E106: =B63 -> 1.5767986
A107: Value Creation / Destruction | B107: -41.186055 | C107: -11.919076 | D107: 17.347903 | E107: 46.614881
A108: Cumulative Incremental FCF | B108: 107.22875 | C108: 137.48269 | D108: 167.73663 | E108: 197.99057
A109: Maximum Value-Creating Purchase Price | B109: 345.67422 | C109: 374.9412 | D109: 404.20817 | E109: 433.47515
A110: Maximum EPS-Neutral Purchase Price | B110: 320.64955 | C110: 538.56348 | D110: 756.47741 | E110: 974.39134
A114: Financing Mix Sensitivity
A115: Cash Consideration | B115: 1 | C115: 0.75 | D115: 0.5 | E115: 0.25 | F115: 0
A116: Cash Consideration | B116: =B115*'M&A Analysis'!B16 -> 438.18787 | C116: =C115*'M&A Analysis'!B16 -> 328.64091 | D116: =D115*'M&A Analysis'!B16 -> 219.09394 | E116: =E115*'M&A Analysis'!B16 -> 109.54697 | F116: =F115*'M&A Analysis'!B16 -> 0
A117: Debt Consideration | B117: =(1-B115)*'M&A Analysis'!B16 -> 0 | C117: =(1-C115)*'M&A Analysis'!B16 -> 109.54697 | D117: =(1-D115)*'M&A Analysis'!B16 -> 219.09394 | E117: =(1-E115)*'M&A Analysis'!B16 -> 328.64091 | F117: =(1-F115)*'M&A Analysis'!B16 -> 438.18787
A118: Share Consideration | B118: 0 | C118: 0 | D118: 0 | E118: 0 | F118: 0
A119: New Debt | B119: =B117 -> 0 | C119: =C117 -> 109.54697 | D119: =D117 -> 219.09394 | E119: =E117 -> 328.64091 | F119: =F117 -> 438.18787
A120: Incremental Interest Expense | B120: =B119*'M&A Analysis'!B39 -> 0 | C120: =C119*'M&A Analysis'!B39 -> 7.3067828 | D120: =D119*'M&A Analysis'!B39 -> 14.613566 | E120: =E119*'M&A Analysis'!B39 -> 21.920348 | F120: =F119*'M&A Analysis'!B39 -> 29.227131
A121: Pro Forma Cash | B121: -96.187874 | C121: 13.359094 | D121: 122.90606 | E121: 232.45303 | F121: 342
A122: Pro Forma Net Debt / EBITDA | B122: =(('M&A Analysis'!B52+B117)-('M&A Analysis'!B51-B116))/'M&A Analysis'!C54 -> 1.5767986 | C122: =(('M&A Analysis'!B52+C117)-('M&A Analysis'!B51-C116))/'M&A Analysis'!C54 -> 1.5767986 | D122: =(('M&A Analysis'!B52+D117)-('M&A Analysis'!B51-D116))/'M&A Analysis'!C54 -> 1.5767986 | E122: =(('M&A Analysis'!B52+E117)-('M&A Analysis'!B51-E116))/'M&A Analysis'!C54 -> 1.5767986 | F122: =(('M&A Analysis'!B52+F117)-('M&A Analysis'!B51-F116))/'M&A Analysis'!C54 -> 1.5767986
A123: EPS Accretion / Dilution FY28 | B123: =((SUM('Accretion & Dilution'!D75:D78)-'Accretion & Dilution'!D79-(B120*(1-Valuation!B10)))/'Accretion & Dilution'!D84)/'Accretion & Dilution'!D85-1 -> 0.076065026 | C123: =((SUM('Accretion & Dilution'!D75:D78)-'Accretion & Dilution'!D79-(C120*(1-Valuation!B10)))/'Accretion & Dilution'!D84)/'Accretion & Dilution'!D85-1 -> 0.055528536 | D123: =((SUM('Accretion & Dilution'!D75:D78)-'Accretion & Dilution'!D79-(D120*(1-Valuation!B10)))/'Accretion & Dilution'!D84)/'Accretion & Dilution'!D85-1 -> 0.034992046 | E123: =((SUM('Accretion & Dilution'!D75:D78)-'Accretion & Dilution'!D79-(E120*(1-Valuation!B10)))/'Accretion & Dilution'!D84)/'Accretion & Dilution'!D85-1 -> 0.014455556 | F123: =((SUM('Accretion & Dilution'!D75:D78)-'Accretion & Dilution'!D79-(F120*(1-Valuation!B10)))/'Accretion & Dilution'!D84)/'Accretion & Dilution'!D85-1 -> -0.0060809346
A124: Cumulative Incremental FCF | B124: 169.92757 | C124: 168.8321 | D124: 167.73663 | E124: 166.64116 | F124: 165.54569
A125: Value Creation / Destruction | B125: 19.363417 | C125: 18.35566 | D125: 17.347903 | E125: 16.340145 | F125: 15.332388
A129: Investment Recommendation
A130: Transaction Status | B130: Proceed with 15% acquisition premium with value creation of £17.4m (4.5% of purchase price), with EPS accretion from FY28
A131: Key Financial Rationale | B131: Value creation from procurement, distribution, head-office ad revenue synergies, cumulative incremental FCF reaches ~£167.7m with EPS accretion reaching 31% by FY30
A132: Key Risk | B132: Limited valuation headroom as value creation falls to ~0% at 20.2% premium. Execution and synergy risks mean B&M should avoid exceeding proposed 15% premium
